[
  {
    "agency": "Fire",
    "alert_level": "Advice",
    "event_type": "incident",
    "title": "GRASS AND BUSH FIRE - BONNER",
    "id": "018687-28122024",
    "latitude": "-35.1511192322",
    "longitude": "149.1402740479",
    "region": "act",
    "time_of_call": "28 Dec 2024 12:50:59",
    "status": "On Scene",
    "status_description": "",
    "status_icon": "/sites/default/files/alert-svgs/narrow%20black%20yellow%20triangle.svg",
    "status_filter_label": "Active",
    "type": "GRASS AND BUSH FIRE",
    "type_description": "",
    "type_icon": "/sites/default/files/incident-type-svgs/fire_1_0_4.svg",
    "location": "DJERRKURA STREET, ROY MARIKA STREET, BONNER, 2914",
    "updated": "28 Dec 2024 17:17:01"
  },
  {
    "agency": "Ambulance",
    "alert_level": "",
    "event_type": "incident",
    "title": "AMBULANCE RESPONSE - O'CONNOR",
    "id": "079216-28122024",
    "latitude": "-35.256876",
    "longitude": "149.111857",
    "region": "act",
    "time_of_call": "28 Dec 2024 15:46:24",
    "status": "On Scene",
    "status_description": "",
    "status_icon": "/sites/default/files/type-ambulance-svgs/narrow%20ambulance%20blue-0_1.svg",
    "status_filter_label": "On Scene",
    "type": "AMBULANCE RESPONSE",
    "location": "O'CONNOR",
    "updated": "28 Dec 2024 17:19:49"
  },
  {
    "agency": "Ambulance",
    "alert_level": "",
    "event_type": "incident",
    "title": "AMBULANCE RESPONSE - CONDER",
    "id": "079221-28122024",
    "latitude": "-35.458351",
    "longitude": "149.106348",
    "region": "act",
    "time_of_call": "28 Dec 2024 16:03:59",
    "status": "Finished",
    "status_description": "",
    "status_icon": "/sites/default/files/type-ambulance-svgs/narrow%20ambulance%20triangle-0.svg",
    "status_filter_label": "Finished",
    "type": "AMBULANCE RESPONSE",
    "location": "CONDER",
    "updated": "28 Dec 2024 17:27:41"
  },
  {
    "agency": "Ambulance",
    "alert_level": "",
    "event_type": "incident",
    "title": "AMBULANCE RESPONSE - CAMPBELL",
    "id": "079226-28122024",
    "latitude": "-35.288663",
    "longitude": "149.155928",
    "region": "act",
    "time_of_call": "28 Dec 2024 16:25:35",
    "status": "On Scene",
    "status_description": "",
    "status_icon": "/sites/default/files/type-ambulance-svgs/narrow%20ambulance%20blue-0_1.svg",
    "status_filter_label": "On Scene",
    "type": "AMBULANCE RESPONSE",
    "location": "CAMPBELL",
    "updated": "28 Dec 2024 17:42:45"
  },
  {
    "agency": "Ambulance",
    "alert_level": "",
    "event_type": "incident",
    "title": "AMBULANCE RESPONSE - HOLT",
    "id": "079227-28122024",
    "latitude": "-35.224201",
    "longitude": "149.013141",
    "region": "act",
    "time_of_call": "28 Dec 2024 16:40:46",
    "status": "On Scene",
    "status_description": "",
    "status_icon": "/sites/default/files/type-ambulance-svgs/narrow%20ambulance%20blue-0_1.svg",
    "status_filter_label": "On Scene",
    "type": "AMBULANCE RESPONSE",
    "location": "HOLT",
    "updated": "28 Dec 2024 17:28:37"
  },
  {
    "agency": "Ambulance",
    "alert_level": "",
    "event_type": "incident",
    "title": "AMBULANCE RESPONSE - STIRLING",
    "id": "079228-28122024",
    "latitude": "-35.351472",
    "longitude": "149.046603",
    "region": "act",
    "time_of_call": "28 Dec 2024 16:42:01",
    "status": "On Scene",
    "status_description": "",
    "status_icon": "/sites/default/files/type-ambulance-svgs/narrow%20ambulance%20blue-0_1.svg",
    "status_filter_label": "On Scene",
    "type": "AMBULANCE RESPONSE",
    "location": "STIRLING",
    "updated": "28 Dec 2024 17:24:43"
  },
  {
    "agency": "Ambulance",
    "alert_level": "",
    "event_type": "incident",
    "title": "AMBULANCE RESPONSE - BELCONNEN",
    "id": "079229-28122024",
    "latitude": "-35.235936",
    "longitude": "149.066372",
    "region": "act",
    "time_of_call": "28 Dec 2024 16:57:51",
    "status": "On Scene",
    "status_description": "",
    "status_icon": "/sites/default/files/type-ambulance-svgs/narrow%20ambulance%20blue-0_1.svg",
    "status_filter_label": "On Scene",
    "type": "AMBULANCE RESPONSE",
    "location": "BELCONNEN",
    "updated": "28 Dec 2024 17:45:57"
  },
  {
    "agency": "Ambulance",
    "alert_level": "",
    "event_type": "incident",
    "title": "AMBULANCE RESPONSE - CALWELL",
    "id": "079231-28122024",
    "latitude": "-35.441132",
    "longitude": "149.107648",
    "region": "act",
    "time_of_call": "28 Dec 2024 17:34:04",
    "status": "Resource Allocation Pending",
    "status_description": "",
    "status_icon": "/sites/default/files/type-ambulance-svgs/narrow%20ambulance%20blue-0_2.svg",
    "status_filter_label": "Resource Allocation Pending",
    "type": "AMBULANCE RESPONSE",
    "location": "CALWELL",
    "updated": "28 Dec 2024 17:48:04"
  },
  {
    "agency": "Ambulance",
    "alert_level": "",
    "event_type": "incident",
    "title": "AMBULANCE RESPONSE - THROSBY",
    "id": "079232-28122024",
    "latitude": "-35.187595",
    "longitude": "149.161141",
    "region": "act",
    "time_of_call": "28 Dec 2024 17:36:42",
    "status": "Resource Allocation Pending",
    "status_description": "",
    "status_icon": "/sites/default/files/type-ambulance-svgs/narrow%20ambulance%20blue-0_2.svg",
    "status_filter_label": "Resource Allocation Pending",
    "type": "AMBULANCE RESPONSE",
    "location": "THROSBY",
    "updated": "28 Dec 2024 17:43:23"
  },
  {
    "agency": "Ambulance",
    "alert_level": "",
    "event_type": "incident",
    "title": "AMBULANCE RESPONSE - MCKELLAR",
    "id": "079234-28122024",
    "latitude": "-35.216327",
    "longitude": "149.076954",
    "region": "act",
    "time_of_call": "28 Dec 2024 17:42:20",
    "status": "Units On Route",
    "status_description": "",
    "status_icon": "/sites/default/files/type-ambulance-svgs/narrow%20ambulance%20blue-0_3.svg",
    "status_filter_label": "Units On Route",
    "type": "AMBULANCE RESPONSE",
    "location": "MCKELLAR",
    "updated": "28 Dec 2024 17:45:13"
  },
  {
    "agency": "Ambulance",
    "alert_level": "",
    "event_type": "incident",
    "title": "AMBULANCE RESPONSE - BRADDON",
    "id": "079235-28122024",
    "latitude": "-35.270314",
    "longitude": "149.135874",
    "region": "act",
    "time_of_call": "28 Dec 2024 17:48:16",
    "status": "Resource Allocation Pending",
    "status_description": "",
    "status_icon": "/sites/default/files/type-ambulance-svgs/narrow%20ambulance%20blue-0_2.svg",
    "status_filter_label": "Resource Allocation Pending",
    "type": "AMBULANCE RESPONSE",
    "location": "BRADDON",
    "updated": "28 Dec 2024 17:48:35"
  },
  {
    "title": "ENDEAVOUR DR, BALRANALD",
    "id": "https___incidents_rfs_nsw_gov_au_api_v1_incidents_579349",
    "link": "http://www.rfs.nsw.gov.au/fire-information/fires-near-me",
    "link_text": "View more",
    "latitude": "-34.646060943",
    "longitude": "143.542129516",
    "region": "nsw",
    "time_of_call": "28 Dec 2024 16:18:00",
    "event_type": "burnt area",
    "status": "Under control",
    "status_description": "",
    "status_icon": "/sites/default/files/alert-svgs/narrow%20black%20yellow%20triangle.svg",
    "status_filter_label": "Active",
    "alert_level": "Advice",
    "location": "ENDEAVOUR DR, BALRANALD 2715",
    "council_area": "Balranald",
    "type": "Bush Fire",
    "type_description": "",
    "type_icon": "/sites/default/files/incident-type-svgs/fire_1_0_2.svg",
    "fire": "Yes",
    "size": "5 ha",
    "responsible_agency": "Rural Fire Service",
    "updated": "28 Dec 2024 16:18"
  },
  {
    "title": "Running Waters, Barry Way Kosciuszko ",
    "id": "https___incidents_rfs_nsw_gov_au_api_v1_incidents_580515",
    "link": "http://www.rfs.nsw.gov.au/fire-information/fires-near-me",
    "link_text": "View more",
    "latitude": "-36.8271484369999",
    "longitude": "148.401779175",
    "region": "nsw",
    "time_of_call": "28 Dec 2024 09:30:00",
    "event_type": "burnt area",
    "status": "Under control",
    "status_description": "",
    "status_icon": "/sites/default/files/alert-svgs/narrow%20black%20yellow%20triangle.svg",
    "status_filter_label": "Active",
    "alert_level": "Advice",
    "location": "BARRY WAY, INGEEGOODBEE 2627",
    "council_area": "Snowy Monaro",
    "type": "Bush Fire",
    "type_description": "",
    "type_icon": "/sites/default/files/incident-type-svgs/fire_1_0_2.svg",
    "fire": "Yes",
    "size": "2 ha",
    "responsible_agency": "NSW National Parks and Wildlife Service",
    "updated": "28 Dec 2024 09:30"
  },
  {
    "title": "HILL END RD, HILL END",
    "id": "https___incidents_rfs_nsw_gov_au_api_v1_incidents_580952",
    "link": "http://www.rfs.nsw.gov.au/fire-information/fires-near-me",
    "link_text": "View more",
    "latitude": "-33.0547978399999",
    "longitude": "149.471361708",
    "region": "nsw",
    "time_of_call": "28 Dec 2024 13:22:00",
    "event_type": "burnt area",
    "status": "Under control",
    "status_description": "",
    "status_icon": "/sites/default/files/alert-svgs/narrow%20black%20yellow%20triangle.svg",
    "status_filter_label": "Active",
    "alert_level": "Advice",
    "location": "3167 HILL END RD, HILL END 2850",
    "council_area": "Bathurst",
    "type": "Grass Fire",
    "type_description": "",
    "type_icon": "/sites/default/files/incident-type-svgs/fire_1_0_5.svg",
    "fire": "Yes",
    "size": "460 ha",
    "responsible_agency": "Rural Fire Service",
    "updated": "28 Dec 2024 13:22"
  },
  {
    "title": "VIOLET HILL RD, VIOLET HILL",
    "id": "https___incidents_rfs_nsw_gov_au_api_v1_incidents_580984",
    "link": "http://www.rfs.nsw.gov.au/fire-information/fires-near-me",
    "link_text": "View more",
    "latitude": "-32.4699058539999",
    "longitude": "152.326950073",
    "region": "nsw",
    "time_of_call": "28 Dec 2024 14:46:00",
    "event_type": "burnt area",
    "status": "Under control",
    "status_description": "",
    "status_icon": "/sites/default/files/alert-svgs/narrow%20black%20yellow%20triangle.svg",
    "status_filter_label": "Active",
    "alert_level": "Advice",
    "location": "VIOLET HILL RD, VIOLET HILL 2423",
    "council_area": "Mid-Coast",
    "type": "Bush Fire",
    "type_description": "",
    "type_icon": "/sites/default/files/incident-type-svgs/fire_1_0_2.svg",
    "fire": "Yes",
    "size": "89 ha",
    "responsible_agency": "NSW National Parks and Wildlife Service",
    "updated": "28 Dec 2024 14:46"
  },
  {
    "title": "COMBOYNE RD, COMBOYNE",
    "id": "https___incidents_rfs_nsw_gov_au_api_v1_incidents_581070",
    "link": "http://www.rfs.nsw.gov.au/fire-information/fires-near-me",
    "link_text": "View more",
    "latitude": "-31.5167522429999",
    "longitude": "152.501846313",
    "region": "nsw",
    "time_of_call": "28 Dec 2024 15:03:00",
    "event_type": "burnt area",
    "status": "Under control",
    "status_description": "",
    "status_icon": "/sites/default/files/alert-svgs/narrow%20black%20yellow%20triangle.svg",
    "status_filter_label": "Active",
    "alert_level": "Advice",
    "location": "COMBOYNE RD, COMBOYNE 2429",
    "council_area": "Port Macquarie-Hastings",
    "type": "Bush Fire",
    "type_description": "",
    "type_icon": "/sites/default/files/incident-type-svgs/fire_1_0_2.svg",
    "fire": "Yes",
    "size": "0 ha",
    "responsible_agency": "Rural Fire Service",
    "updated": "28 Dec 2024 15:03"
  },
  {
    "title": "COMMISSION RD, HOWES VALLEY",
    "id": "https___incidents_rfs_nsw_gov_au_api_v1_incidents_581302",
    "link": "http://www.rfs.nsw.gov.au/fire-information/fires-near-me",
    "link_text": "View more",
    "latitude": "-32.851154327",
    "longitude": "150.78918457",
    "region": "nsw",
    "time_of_call": "28 Dec 2024 16:00:00",
    "event_type": "burnt area",
    "status": "Under control",
    "status_description": "",
    "status_icon": "/sites/default/files/alert-svgs/narrow%20black%20yellow%20triangle.svg",
    "status_filter_label": "Active",
    "alert_level": "Advice",
    "location": "401 COMMISSION RD, HOWES VALLEY 2330",
    "council_area": "Singleton",
    "type": "Bush Fire",
    "type_description": "",
    "type_icon": "/sites/default/files/incident-type-svgs/fire_1_0_2.svg",
    "fire": "Yes",
    "size": "12 ha",
    "responsible_agency": "Rural Fire Service",
    "updated": "28 Dec 2024 16:00"
  },
  {
    "title": "MURRAY ROSE AV",
    "id": "https___incidents_rfs_nsw_gov_au_api_v1_incidents_581350",
    "link": "http://www.rfs.nsw.gov.au/fire-information/fires-near-me",
    "link_text": "View more",
    "latitude": "-33.844589234",
    "longitude": "151.074630738",
    "region": "nsw",
    "time_of_call": "27 Dec 2024 00:22:00",
    "event_type": "burnt area",
    "status": "Under control",
    "alert_level": "Not Applicable",
    "location": "RFS - VICTORIAN DEPLOYMENT 4 MURRAY ROSE AV, SYDNEY OLYMPIC PARK 2127",
    "council_area": "City of Parramatta",
    "type": "Assist Other Agency",
    "fire": "No",
    "size": "0 ha",
    "responsible_agency": "Rural Fire Service",
    "updated": "27 Dec 2024 00:22"
  },
  {
    "title": "MILL CREEK RD, STROUD",
    "id": "https___incidents_rfs_nsw_gov_au_api_v1_incidents_581381",
    "link": "http://www.rfs.nsw.gov.au/fire-information/fires-near-me",
    "link_text": "View more",
    "latitude": "-32.284883253",
    "longitude": "151.994218826",
    "region": "nsw",
    "time_of_call": "27 Dec 2024 23:49:00",
    "event_type": "burnt area",
    "status": "Under control",
    "status_description": "",
    "status_icon": "/sites/default/files/alert-svgs/narrow%20black%20yellow%20triangle.svg",
    "status_filter_label": "Active",
    "alert_level": "Advice",
    "location": "COPPERMINE 1279 MILL CREEK RD, STROUD 2425",
    "council_area": "Mid-Coast",
    "type": "Grass Fire",
    "type_description": "",
    "type_icon": "/sites/default/files/incident-type-svgs/fire_1_0_5.svg",
    "fire": "Yes",
    "size": "0 ha",
    "responsible_agency": "Rural Fire Service",
    "updated": "27 Dec 2024 23:49"
  },
  {
    "title": "MOODYS HILL RD, MARAGLE",
    "id": "https___incidents_rfs_nsw_gov_au_api_v1_incidents_581470",
    "link": "http://www.rfs.nsw.gov.au/fire-information/fires-near-me",
    "link_text": "View more",
    "latitude": "-35.8361630159999",
    "longitude": "148.192902556",
    "region": "nsw",
    "time_of_call": "28 Dec 2024 16:41:00",
    "event_type": "burnt area",
    "status": "Under control",
    "status_description": "",
    "status_icon": "/sites/default/files/alert-svgs/narrow%20black%20yellow%20triangle.svg",
    "status_filter_label": "Active",
    "alert_level": "Advice",
    "location": "MOODYS HILL RD, MARAGLE 2653",
    "council_area": "Snowy Valleys",
    "type": "Bush Fire",
    "type_description": "",
    "type_icon": "/sites/default/files/incident-type-svgs/fire_1_0_2.svg",
    "fire": "Yes",
    "size": "13 ha",
    "responsible_agency": "Rural Fire Service",
    "updated": "28 Dec 2024 16:41"
  },
  {
    "title": "MCKINLEY RD, MERRIWAGGA",
    "id": "https___incidents_rfs_nsw_gov_au_api_v1_incidents_581481",
    "link": "http://www.rfs.nsw.gov.au/fire-information/fires-near-me",
    "link_text": "View more",
    "latitude": "-33.89521408",
    "longitude": "145.449890137",
    "region": "nsw",
    "time_of_call": "28 Dec 2024 16:23:00",
    "event_type": "burnt area",
    "status": "Under control",
    "alert_level": "Not Applicable",
    "location": "MCKINLEY RD, MERRIWAGGA 2652",
    "council_area": "Carrathool",
    "type": "Haystack fire",
    "type_description": "",
    "type_icon": "/sites/default/files/incident-type-svgs/fire_1_0_6.svg",
    "fire": "Yes",
    "size": "0 ha",
    "responsible_agency": "Rural Fire Service",
    "updated": "28 Dec 2024 16:23"
  },
  {
    "title": "Patons Hut",
    "id": "https___incidents_rfs_nsw_gov_au_api_v1_incidents_581586",
    "link": "http://www.rfs.nsw.gov.au/fire-information/fires-near-me",
    "link_text": "View more",
    "latitude": "-36.0586965649999",
    "longitude": "148.314403367",
    "region": "nsw",
    "time_of_call": "28 Dec 2024 14:46:00",
    "event_type": "burnt area",
    "status": "Being controlled",
    "status_description": "",
    "status_icon": "/sites/default/files/alert-svgs/narrow%20black%20yellow%20triangle.svg",
    "status_filter_label": "Active",
    "alert_level": "Advice",
    "location": "DARGALS TRL, JAGUMBA 2642",
    "council_area": "Snowy Valleys",
    "type": "Bush Fire",
    "type_description": "",
    "type_icon": "/sites/default/files/incident-type-svgs/fire_1_0_2.svg",
    "fire": "Yes",
    "size": "21 ha",
    "responsible_agency": "NSW National Parks and Wildlife Service",
    "updated": "28 Dec 2024 14:46"
  },
  {
    "title": "TRINKEY FOREST RD, TAMBAR SPRINGS",
    "id": "https___incidents_rfs_nsw_gov_au_api_v1_incidents_581595",
    "link": "http://www.rfs.nsw.gov.au/fire-information/fires-near-me",
    "link_text": "View more",
    "latitude": "-31.3566226959999",
    "longitude": "149.90991211",
    "region": "nsw",
    "time_of_call": "28 Dec 2024 11:30:00",
    "event_type": "burnt area",
    "status": "Under control",
    "status_description": "",
    "status_icon": "/sites/default/files/alert-svgs/narrow%20black%20yellow%20triangle.svg",
    "status_filter_label": "Active",
    "alert_level": "Advice",
    "location": "TRINKEY FOREST RD, TAMBAR SPRINGS 2381",
    "council_area": "Gunnedah",
    "type": "Grass Fire",
    "type_description": "",
    "type_icon": "/sites/default/files/incident-type-svgs/fire_1_0_5.svg",
    "fire": "Yes",
    "size": "0 ha",
    "responsible_agency": "Rural Fire Service",
    "updated": "28 Dec 2024 11:30"
  },
  {
    "title": "PORT MACQUARIE RD, BOGEE",
    "id": "https___incidents_rfs_nsw_gov_au_api_v1_incidents_581599",
    "link": "http://www.rfs.nsw.gov.au/fire-information/fires-near-me",
    "link_text": "View more",
    "latitude": "-33.015213122",
    "longitude": "150.050316813",
    "region": "nsw",
    "time_of_call": "28 Dec 2024 15:14:00",
    "event_type": "burnt area",
    "status": "Under control",
    "status_description": "",
    "status_icon": "/sites/default/files/alert-svgs/narrow%20black%20yellow%20triangle.svg",
    "status_filter_label": "Active",
    "alert_level": "Advice",
    "location": "1046 PORT MACQUARIE RD, BOGEE 2849",
    "council_area": "Lithgow",
    "type": "Bush Fire",
    "type_description": "",
    "type_icon": "/sites/default/files/incident-type-svgs/fire_1_0_2.svg",
    "fire": "Yes",
    "size": "1 ha",
    "responsible_agency": "NSW National Parks and Wildlife Service",
    "updated": "28 Dec 2024 15:14"
  },
  {
    "title": "STEELS ROAD",
    "id": "https___incidents_rfs_nsw_gov_au_api_v1_incidents_581610",
    "link": "http://www.rfs.nsw.gov.au/fire-information/fires-near-me",
    "link_text": "View more",
    "latitude": "-31.840951919",
    "longitude": "150.820907592",
    "region": "nsw",
    "time_of_call": "28 Dec 2024 11:41:00",
    "event_type": "burnt area",
    "status": "Under control",
    "status_description": "",
    "status_icon": "/sites/default/files/alert-svgs/narrow%20black%20yellow%20triangle.svg",
    "status_filter_label": "Active",
    "alert_level": "Advice",
    "location": "STEELS ROAD",
    "council_area": "Upper Hunter",
    "type": "Bush Fire",
    "type_description": "",
    "type_icon": "/sites/default/files/incident-type-svgs/fire_1_0_2.svg",
    "fire": "Yes",
    "size": "1 ha",
    "responsible_agency": "Rural Fire Service",
    "updated": "28 Dec 2024 11:41"
  },
  {
    "title": "COOLAWINE TRAIL, BROKE",
    "id": "https___incidents_rfs_nsw_gov_au_api_v1_incidents_581612",
    "link": "http://www.rfs.nsw.gov.au/fire-information/fires-near-me",
    "link_text": "View more",
    "latitude": "-32.8163146979999",
    "longitude": "151.099792481",
    "region": "nsw",
    "time_of_call": "28 Dec 2024 14:24:00",
    "event_type": "burnt area",
    "status": "Being controlled",
    "status_description": "",
    "status_icon": "/sites/default/files/alert-svgs/narrow%20black%20yellow%20triangle.svg",
    "status_filter_label": "Active",
    "alert_level": "Advice",
    "location": "OFF COOLAWINE TRAIL",
    "council_area": "Singleton",
    "type": "Bush Fire",
    "type_description": "",
    "type_icon": "/sites/default/files/incident-type-svgs/fire_1_0_2.svg",
    "fire": "Yes",
    "size": "15 ha",
    "responsible_agency": "Rural Fire Service",
    "updated": "28 Dec 2024 14:24"
  },
  {
    "title": "HUNTER RD, GUNDY",
    "id": "https___incidents_rfs_nsw_gov_au_api_v1_incidents_581617",
    "link": "http://www.rfs.nsw.gov.au/fire-information/fires-near-me",
    "link_text": "View more",
    "latitude": "-32.0121516679999",
    "longitude": "151.07093811",
    "region": "nsw",
    "time_of_call": "28 Dec 2024 10:57:00",
    "event_type": "burnt area",
    "status": "Under control",
    "status_description": "",
    "status_icon": "/sites/default/files/alert-svgs/narrow%20black%20yellow%20triangle.svg",
    "status_filter_label": "Active",
    "alert_level": "Advice",
    "location": "HUNTER RD, GUNDY 2337",
    "council_area": "Upper Hunter",
    "type": "Bush Fire",
    "type_description": "",
    "type_icon": "/sites/default/files/incident-type-svgs/fire_1_0_2.svg",
    "fire": "Yes",
    "size": "0 ha",
    "responsible_agency": "Rural Fire Service",
    "updated": "28 Dec 2024 10:57"
  },
  {
    "title": "RIVER RD, BOWLING ALLEY POINT",
    "id": "https___incidents_rfs_nsw_gov_au_api_v1_incidents_581619",
    "link": "http://www.rfs.nsw.gov.au/fire-information/fires-near-me",
    "link_text": "View more",
    "latitude": "-31.38401413",
    "longitude": "151.168899536",
    "region": "nsw",
    "time_of_call": "28 Dec 2024 17:27:00",
    "event_type": "burnt area",
    "status": "Under control",
    "status_description": "",
    "status_icon": "/sites/default/files/alert-svgs/narrow%20black%20yellow%20triangle.svg",
    "status_filter_label": "Active",
    "alert_level": "Advice",
    "location": "RIVER RD, BOWLING ALLEY POINT 2340",
    "council_area": "Tamworth",
    "type": "Bush Fire",
    "type_description": "",
    "type_icon": "/sites/default/files/incident-type-svgs/fire_1_0_2.svg",
    "fire": "Yes",
    "size": "2 ha",
    "responsible_agency": "Rural Fire Service",
    "updated": "28 Dec 2024 17:27"
  },
  {
    "title": "BOYS ARM, HOWES VALLEY",
    "id": "https___incidents_rfs_nsw_gov_au_api_v1_incidents_581625",
    "link": "http://www.rfs.nsw.gov.au/fire-information/fires-near-me",
    "link_text": "View more",
    "latitude": "-32.791567749",
    "longitude": "150.798554421",
    "region": "nsw",
    "time_of_call": "28 Dec 2024 16:48:00",
    "event_type": "burnt area",
    "status": "Being controlled",
    "status_description": "",
    "status_icon": "/sites/default/files/alert-svgs/narrow%20black%20yellow%20triangle.svg",
    "status_filter_label": "Active",
    "alert_level": "Advice",
    "location": "BOYS ARM, HOWES VALLEY 2330",
    "council_area": "Singleton",
    "type": "Bush Fire",
    "type_description": "",
    "type_icon": "/sites/default/files/incident-type-svgs/fire_1_0_2.svg",
    "fire": "Yes",
    "size": "94 ha",
    "responsible_agency": "Rural Fire Service",
    "updated": "28 Dec 2024 16:48"
  },
  {
    "title": "REEDY CREEK, GARLAND VALLEY",
    "id": "https___incidents_rfs_nsw_gov_au_api_v1_incidents_581628",
    "link": "http://www.rfs.nsw.gov.au/fire-information/fires-near-me",
    "link_text": "View more",
    "latitude": "-32.869350434",
    "longitude": "150.760055542",
    "region": "nsw",
    "time_of_call": "28 Dec 2024 16:59:00",
    "event_type": "burnt area",
    "status": "Being controlled",
    "status_description": "",
    "status_icon": "/sites/default/files/alert-svgs/narrow%20black%20yellow%20triangle.svg",
    "status_filter_label": "Active",
    "alert_level": "Advice",
    "location": "NR 6474 PUTTY RD, GARLAND VALLEY 2330",
    "council_area": "Singleton",
    "type": "Bush Fire",
    "type_description": "",
    "type_icon": "/sites/default/files/incident-type-svgs/fire_1_0_2.svg",
    "fire": "Yes",
    "size": "5 ha",
    "responsible_agency": "Rural Fire Service",
    "updated": "28 Dec 2024 16:59"
  },
  {
    "title": "Station Creek, THE PILLIGA",
    "id": "https___incidents_rfs_nsw_gov_au_api_v1_incidents_581636",
    "link": "http://www.rfs.nsw.gov.au/fire-information/fires-near-me",
    "link_text": "View more",
    "latitude": "-30.819704056",
    "longitude": "149.446166992",
    "region": "nsw",
    "time_of_call": "28 Dec 2024 16:40:00",
    "event_type": "burnt area",
    "status": "Under control",
    "status_description": "",
    "status_icon": "/sites/default/files/alert-svgs/narrow%20black%20yellow%20triangle.svg",
    "status_filter_label": "Active",
    "alert_level": "Advice",
    "location": "NEWELL HWY, THE PILLIGA 2388",
    "council_area": "Narrabri",
    "type": "Bush Fire",
    "type_description": "",
    "type_icon": "/sites/default/files/incident-type-svgs/fire_1_0_2.svg",
    "fire": "Yes",
    "size": "103 ha",
    "responsible_agency": "Rural Fire Service",
    "updated": "28 Dec 2024 16:40"
  },
  {
    "title": "YELLOW ROCK RD, BROKE",
    "id": "https___incidents_rfs_nsw_gov_au_api_v1_incidents_581641",
    "link": "http://www.rfs.nsw.gov.au/fire-information/fires-near-me",
    "link_text": "View more",
    "latitude": "-32.7990894079999",
    "longitude": "151.134667397",
    "region": "nsw",
    "time_of_call": "28 Dec 2024 14:14:00",
    "event_type": "burnt area",
    "status": "Under control",
    "status_description": "",
    "status_icon": "/sites/default/files/alert-svgs/narrow%20black%20yellow%20triangle.svg",
    "status_filter_label": "Active",
    "alert_level": "Advice",
    "location": "YELLOW ROCK RD, BROKE 2330",
    "council_area": "Singleton",
    "type": "Bush Fire",
    "type_description": "",
    "type_icon": "/sites/default/files/incident-type-svgs/fire_1_0_2.svg",
    "fire": "Yes",
    "size": "2 ha",
    "responsible_agency": "Rural Fire Service",
    "updated": "28 Dec 2024 14:14"
  },
  {
    "title": "OLD DAIRY CONTROL",
    "id": "https___incidents_rfs_nsw_gov_au_api_v1_incidents_581652",
    "link": "http://www.rfs.nsw.gov.au/fire-information/fires-near-me",
    "link_text": "View more",
    "latitude": "-34.8146705629999",
    "longitude": "146.762329102",
    "region": "nsw",
    "time_of_call": "28 Dec 2024 16:23:00",
    "event_type": "burnt area",
    "status": "Under control",
    "status_description": "",
    "status_icon": "/sites/default/files/alert-svgs/narrow%20black%20yellow%20triangle.svg",
    "status_filter_label": "Active",
    "alert_level": "Advice",
    "location": "OLD WAGGA RD, GRONG GRONG 2652",
    "council_area": "Narrandera",
    "type": "Grass Fire",
    "type_description": "",
    "type_icon": "/sites/default/files/incident-type-svgs/fire_1_0_5.svg",
    "fire": "Yes",
    "size": "67 ha",
    "responsible_agency": "Rural Fire Service",
    "updated": "28 Dec 2024 16:23"
  },
  {
    "title": "PARADISE RD, MURRURUNDI",
    "id": "https___incidents_rfs_nsw_gov_au_api_v1_incidents_581653",
    "link": "http://www.rfs.nsw.gov.au/fire-information/fires-near-me",
    "link_text": "View more",
    "latitude": "-31.781251907",
    "longitude": "150.823928833",
    "region": "nsw",
    "time_of_call": "28 Dec 2024 10:45:00",
    "event_type": "burnt area",
    "status": "Under control",
    "status_description": "",
    "status_icon": "/sites/default/files/alert-svgs/narrow%20black%20yellow%20triangle.svg",
    "status_filter_label": "Active",
    "alert_level": "Advice",
    "location": "1 PARADISE RD, MURRURUNDI 2338",
    "council_area": "Upper Hunter",
    "type": "Grass Fire",
    "type_description": "",
    "type_icon": "/sites/default/files/incident-type-svgs/fire_1_0_5.svg",
    "fire": "Yes",
    "size": "1 ha",
    "responsible_agency": "Rural Fire Service",
    "updated": "28 Dec 2024 10:45"
  },
  {
    "title": "PUTTY RD, COLO HEIGHTS",
    "id": "https___incidents_rfs_nsw_gov_au_api_v1_incidents_581660",
    "link": "http://www.rfs.nsw.gov.au/fire-information/fires-near-me",
    "link_text": "View more",
    "latitude": "-33.260757446",
    "longitude": "150.694641113",
    "region": "nsw",
    "time_of_call": "28 Dec 2024 12:48:00",
    "event_type": "burnt area",
    "status": "Under control",
    "status_description": "",
    "status_icon": "/sites/default/files/alert-svgs/narrow%20black%20yellow%20triangle.svg",
    "status_filter_label": "Active",
    "alert_level": "Advice",
    "location": "PUTTY RD, COLO HEIGHTS 2756",
    "council_area": "Hawkesbury",
    "type": "Bush Fire",
    "type_description": "",
    "type_icon": "/sites/default/files/incident-type-svgs/fire_1_0_2.svg",
    "fire": "Yes",
    "size": "10 ha",
    "responsible_agency": "Rural Fire Service",
    "updated": "28 Dec 2024 12:48"
  },
  {
    "title": "PUTTY VALLEY RD, PUTTY",
    "id": "https___incidents_rfs_nsw_gov_au_api_v1_incidents_581664",
    "link": "http://www.rfs.nsw.gov.au/fire-information/fires-near-me",
    "link_text": "View more",
    "latitude": "-32.882072449",
    "longitude": "150.637390137",
    "region": "nsw",
    "time_of_call": "28 Dec 2024 16:20:00",
    "event_type": "burnt area",
    "status": "Being controlled",
    "status_description": "",
    "status_icon": "/sites/default/files/alert-svgs/narrow%20black%20yellow%20triangle.svg",
    "status_filter_label": "Active",
    "alert_level": "Advice",
    "location": "PUTTY VALLEY RD, PUTTY 2330",
    "council_area": "Singleton",
    "type": "Bush Fire",
    "type_description": "",
    "type_icon": "/sites/default/files/incident-type-svgs/fire_1_0_2.svg",
    "fire": "Yes",
    "size": "2 ha",
    "responsible_agency": "Rural Fire Service",
    "updated": "28 Dec 2024 16:20"
  },
  {
    "title": "WOLLOMBI ROAD PAYNES CROSSING",
    "id": "https___incidents_rfs_nsw_gov_au_api_v1_incidents_581666",
    "link": "http://www.rfs.nsw.gov.au/fire-information/fires-near-me",
    "link_text": "View more",
    "latitude": "-32.8585368019999",
    "longitude": "151.057891845",
    "region": "nsw",
    "time_of_call": "28 Dec 2024 16:07:00",
    "event_type": "burnt area",
    "status": "Under control",
    "status_description": "",
    "status_icon": "/sites/default/files/alert-svgs/narrow%20black%20yellow%20triangle.svg",
    "status_filter_label": "Active",
    "alert_level": "Advice",
    "location": "PAYNES CROSSING",
    "council_area": "Singleton",
    "type": "Bush Fire",
    "type_description": "",
    "type_icon": "/sites/default/files/incident-type-svgs/fire_1_0_2.svg",
    "fire": "Yes",
    "size": "1 ha",
    "responsible_agency": "Rural Fire Service",
    "updated": "28 Dec 2024 16:07"
  },
  {
    "title": "MOUNTAIN ST, CHARBON",
    "id": "https___incidents_rfs_nsw_gov_au_api_v1_incidents_581667",
    "link": "http://www.rfs.nsw.gov.au/fire-information/fires-near-me",
    "link_text": "View more",
    "latitude": "-32.8842543439999",
    "longitude": "149.976103306",
    "region": "nsw",
    "time_of_call": "28 Dec 2024 14:16:00",
    "event_type": "burnt area",
    "status": "Being controlled",
    "status_description": "",
    "status_icon": "/sites/default/files/alert-svgs/narrow%20black%20yellow%20triangle.svg",
    "status_filter_label": "Active",
    "alert_level": "Advice",
    "location": "STATION ST, CHARBON 2848",
    "council_area": "Mid-Western",
    "type": "Bush Fire",
    "type_description": "",
    "type_icon": "/sites/default/files/incident-type-svgs/fire_1_0_2.svg",
    "fire": "Yes",
    "size": "12 ha",
    "responsible_agency": "Rural Fire Service",
    "updated": "28 Dec 2024 14:16"
  },
  {
    "title": "MORGANS CREEK RD, BOOROOK",
    "id": "https___incidents_rfs_nsw_gov_au_api_v1_incidents_581668",
    "link": "http://www.rfs.nsw.gov.au/fire-information/fires-near-me",
    "link_text": "View more",
    "latitude": "-28.7988560819999",
    "longitude": "152.280887965",
    "region": "nsw",
    "time_of_call": "28 Dec 2024 15:23:00",
    "event_type": "burnt area",
    "status": "Under control",
    "status_description": "",
    "status_icon": "/sites/default/files/alert-svgs/narrow%20black%20yellow%20triangle.svg",
    "status_filter_label": "Active",
    "alert_level": "Advice",
    "location": "MORGANS CREEK RD, BOOROOK 2372",
    "council_area": "Tenterfield",
    "type": "Bush Fire",
    "type_description": "",
    "type_icon": "/sites/default/files/incident-type-svgs/fire_1_0_2.svg",
    "fire": "Yes",
    "size": "5 ha",
    "responsible_agency": "Rural Fire Service",
    "updated": "28 Dec 2024 15:23"
  },
  {
    "title": "HANNELS SPUR, GEEHI",
    "id": "https___incidents_rfs_nsw_gov_au_api_v1_incidents_581669",
    "link": "http://www.rfs.nsw.gov.au/fire-information/fires-near-me",
    "link_text": "View more",
    "latitude": "-36.391357972",
    "longitude": "148.211452083",
    "region": "nsw",
    "time_of_call": "28 Dec 2024 13:22:00",
    "event_type": "burnt area",
    "status": "Being controlled",
    "status_description": "",
    "status_icon": "/sites/default/files/alert-svgs/narrow%20black%20yellow%20triangle.svg",
    "status_filter_label": "Active",
    "alert_level": "Advice",
    "location": "ALPINE WAY, GEEHI 2642",
    "council_area": "Snowy Valleys",
    "type": "Bush Fire",
    "type_description": "",
    "type_icon": "/sites/default/files/incident-type-svgs/fire_1_0_2.svg",
    "fire": "Yes",
    "size": "1 ha",
    "responsible_agency": "NSW National Parks and Wildlife Service",
    "updated": "28 Dec 2024 13:22"
  },
  {
    "title": "YANGO TRK, PAYNES CROSSING",
    "id": "https___incidents_rfs_nsw_gov_au_api_v1_incidents_581670",
    "link": "http://www.rfs.nsw.gov.au/fire-information/fires-near-me",
    "link_text": "View more",
    "latitude": "-32.956508637",
    "longitude": "150.993591309",
    "region": "nsw",
    "time_of_call": "28 Dec 2024 16:11:00",
    "event_type": "burnt area",
    "status": "Being controlled",
    "status_description": "",
    "status_icon": "/sites/default/files/alert-svgs/narrow%20black%20yellow%20triangle.svg",
    "status_filter_label": "Active",
    "alert_level": "Advice",
    "location": "YANGO TRK, PAYNES CROSSING 2325",
    "council_area": "Cessnock",
    "type": "Bush Fire",
    "type_description": "",
    "type_icon": "/sites/default/files/incident-type-svgs/fire_1_0_2.svg",
    "fire": "Yes",
    "size": "16 ha",
    "responsible_agency": "Rural Fire Service",
    "updated": "28 Dec 2024 16:11"
  },
  {
    "title": "BAG RANGE TRL, WEE JASPER",
    "id": "https___incidents_rfs_nsw_gov_au_api_v1_incidents_581676",
    "link": "http://www.rfs.nsw.gov.au/fire-information/fires-near-me",
    "link_text": "View more",
    "latitude": "-35.1800587829999",
    "longitude": "148.757876939",
    "region": "nsw",
    "time_of_call": "28 Dec 2024 17:15:00",
    "event_type": "burnt area",
    "status": "Being controlled",
    "status_description": "",
    "status_icon": "/sites/default/files/alert-svgs/narrow%20black%20yellow%20triangle.svg",
    "status_filter_label": "Active",
    "alert_level": "Advice",
    "location": "BAG RANGE TRL, WEE JASPER 2582",
    "council_area": "Yass Valley",
    "type": "Bush Fire",
    "type_description": "",
    "type_icon": "/sites/default/files/incident-type-svgs/fire_1_0_2.svg",
    "fire": "Yes",
    "size": "1 ha",
    "responsible_agency": "Rural Fire Service",
    "updated": "28 Dec 2024 17:15"
  },
  {
    "title": "EMU CREEK RD, WIDDEN",
    "id": "https___incidents_rfs_nsw_gov_au_api_v1_incidents_581681",
    "link": "http://www.rfs.nsw.gov.au/fire-information/fires-near-me",
    "link_text": "View more",
    "latitude": "-32.5498161309999",
    "longitude": "150.306900025",
    "region": "nsw",
    "time_of_call": "28 Dec 2024 15:18:00",
    "event_type": "burnt area",
    "status": "Being controlled",
    "status_description": "",
    "status_icon": "/sites/default/files/alert-svgs/narrow%20black%20yellow%20triangle.svg",
    "status_filter_label": "Active",
    "alert_level": "Advice",
    "location": "49 EMU CREEK RD, WIDDEN 2328",
    "council_area": "Muswellbrook",
    "type": "Bush Fire",
    "type_description": "",
    "type_icon": "/sites/default/files/incident-type-svgs/fire_1_0_2.svg",
    "fire": "Yes",
    "size": "12 ha",
    "responsible_agency": "Rural Fire Service",
    "updated": "28 Dec 2024 15:18"
  },
  {
    "title": "GIANTS CREEK RD, GIANTS CREEK",
    "id": "https___incidents_rfs_nsw_gov_au_api_v1_incidents_581686",
    "link": "http://www.rfs.nsw.gov.au/fire-information/fires-near-me",
    "link_text": "View more",
    "latitude": "-32.2658691409999",
    "longitude": "150.54170227",
    "region": "nsw",
    "time_of_call": "28 Dec 2024 17:12:00",
    "event_type": "burnt area",
    "status": "Not yet controlled",
    "status_description": "",
    "status_icon": "/sites/default/files/alert-svgs/narrow%20black%20yellow%20triangle.svg",
    "status_filter_label": "Active",
    "alert_level": "Advice",
    "location": "GIANTS CREEK RD, GIANTS CREEK 2328",
    "council_area": "Muswellbrook",
    "type": "Bush Fire",
    "type_description": "",
    "type_icon": "/sites/default/files/incident-type-svgs/fire_1_0_2.svg",
    "fire": "Yes",
    "size": "0 ha",
    "responsible_agency": "Rural Fire Service",
    "updated": "28 Dec 2024 17:12"
  },
  {
    "title": "BENDENINE RD, BINALONG",
    "id": "https___incidents_rfs_nsw_gov_au_api_v1_incidents_581692",
    "link": "http://www.rfs.nsw.gov.au/fire-information/fires-near-me",
    "link_text": "View more",
    "latitude": "-34.7027415049999",
    "longitude": "148.69222641",
    "region": "nsw",
    "time_of_call": "28 Dec 2024 16:04:00",
    "event_type": "burnt area",
    "status": "Under control",
    "status_description": "",
    "status_icon": "/sites/default/files/alert-svgs/narrow%20black%20yellow%20triangle.svg",
    "status_filter_label": "Active",
    "alert_level": "Advice",
    "location": "GLENLOTHIAN 508 BENDENINE RD, BINALONG 2584",
    "council_area": "Yass Valley",
    "type": "Grass Fire",
    "type_description": "",
    "type_icon": "/sites/default/files/incident-type-svgs/fire_1_0_5.svg",
    "fire": "Yes",
    "size": "87 ha",
    "responsible_agency": "Rural Fire Service",
    "updated": "28 Dec 2024 16:04"
  },
  {
    "title": "DOLOMITE ROAD",
    "id": "https___incidents_rfs_nsw_gov_au_api_v1_incidents_581698",
    "link": "http://www.rfs.nsw.gov.au/fire-information/fires-near-me",
    "link_text": "View more",
    "latitude": "-32.752201081",
    "longitude": "149.855575561",
    "region": "nsw",
    "time_of_call": "28 Dec 2024 12:45:00",
    "event_type": "burnt area",
    "status": "Under control",
    "status_description": "",
    "status_icon": "/sites/default/files/alert-svgs/narrow%20black%20yellow%20triangle.svg",
    "status_filter_label": "Active",
    "alert_level": "Advice",
    "location": "DOLOMITE RD, DUNGEREE 2849",
    "council_area": "Mid-Western",
    "type": "Bush Fire",
    "type_description": "",
    "type_icon": "/sites/default/files/incident-type-svgs/fire_1_0_2.svg",
    "fire": "Yes",
    "size": "2 ha",
    "responsible_agency": "Rural Fire Service",
    "updated": "28 Dec 2024 12:45"
  },
  {
    "title": "MARTINDALE RD, MARTINDALE",
    "id": "https___incidents_rfs_nsw_gov_au_api_v1_incidents_581701",
    "link": "http://www.rfs.nsw.gov.au/fire-information/fires-near-me",
    "link_text": "View more",
    "latitude": "-32.6047325129999",
    "longitude": "150.670471191",
    "region": "nsw",
    "time_of_call": "28 Dec 2024 16:23:00",
    "event_type": "burnt area",
    "status": "Being controlled",
    "status_description": "",
    "status_icon": "/sites/default/files/alert-svgs/narrow%20black%20yellow%20triangle.svg",
    "status_filter_label": "Active",
    "alert_level": "Advice",
    "location": "MARTINDALE RD, MARTINDALE 2328",
    "council_area": "Muswellbrook",
    "type": "Bush Fire",
    "type_description": "",
    "type_icon": "/sites/default/files/incident-type-svgs/fire_1_0_2.svg",
    "fire": "Yes",
    "size": "4 ha",
    "responsible_agency": "Rural Fire Service",
    "updated": "28 Dec 2024 16:23"
  },
  {
    "title": "Nayook Creek",
    "id": "https___incidents_rfs_nsw_gov_au_api_v1_incidents_581708",
    "link": "http://www.rfs.nsw.gov.au/fire-information/fires-near-me",
    "link_text": "View more",
    "latitude": "-33.322180477",
    "longitude": "150.488868705",
    "region": "nsw",
    "time_of_call": "28 Dec 2024 15:52:00",
    "event_type": "burnt area",
    "status": "Being controlled",
    "status_description": "",
    "status_icon": "/sites/default/files/alert-svgs/narrow%20black%20yellow%20triangle.svg",
    "status_filter_label": "Active",
    "alert_level": "Advice",
    "location": "-033.318367",
    "council_area": "Lithgow",
    "type": "Bush Fire",
    "type_description": "",
    "type_icon": "/sites/default/files/incident-type-svgs/fire_1_0_2.svg",
    "fire": "Yes",
    "size": "30 ha",
    "responsible_agency": "NSW National Parks and Wildlife Service",
    "updated": "28 Dec 2024 15:52"
  },
  {
    "title": "SMALLWOOD RD, GLENORIE",
    "id": "https___incidents_rfs_nsw_gov_au_api_v1_incidents_581710",
    "link": "http://www.rfs.nsw.gov.au/fire-information/fires-near-me",
    "link_text": "View more",
    "latitude": "-33.5610008049999",
    "longitude": "150.967814752",
    "region": "nsw",
    "time_of_call": "28 Dec 2024 15:44:00",
    "event_type": "burnt area",
    "status": "Under control",
    "status_description": "",
    "status_icon": "/sites/default/files/alert-svgs/narrow%20black%20yellow%20triangle.svg",
    "status_filter_label": "Active",
    "alert_level": "Advice",
    "location": "65 SMALLWOOD RD, GLENORIE 2157",
    "council_area": "The Hills",
    "type": "Bush Fire",
    "type_description": "",
    "type_icon": "/sites/default/files/incident-type-svgs/fire_1_0_2.svg",
    "fire": "Yes",
    "size": "2 ha",
    "responsible_agency": "Rural Fire Service",
    "updated": "28 Dec 2024 15:44"
  },
  {
    "title": "Paddy's Flat Rd, Tooloom Ck",
    "id": "https___incidents_rfs_nsw_gov_au_api_v1_incidents_581713",
    "link": "http://www.rfs.nsw.gov.au/fire-information/fires-near-me",
    "link_text": "View more",
    "latitude": "-28.656097412",
    "longitude": "152.41166687",
    "region": "nsw",
    "time_of_call": "28 Dec 2024 16:30:00",
    "event_type": "burnt area",
    "status": "Being controlled",
    "status_description": "",
    "status_icon": "/sites/default/files/alert-svgs/narrow%20black%20yellow%20triangle.svg",
    "status_filter_label": "Active",
    "alert_level": "Advice",
    "location": "PADDYS FLAT RD, TOOLOOM 2475",
    "council_area": "Kyogle",
    "type": "Bush Fire",
    "type_description": "",
    "type_icon": "/sites/default/files/incident-type-svgs/fire_1_0_2.svg",
    "fire": "Yes",
    "size": "99 ha",
    "responsible_agency": "Forestry Corporation of NSW",
    "updated": "28 Dec 2024 16:30"
  },
  {
    "title": "NEVERFAIL RD, MERRIWA",
    "id": "https___incidents_rfs_nsw_gov_au_api_v1_incidents_581716",
    "link": "http://www.rfs.nsw.gov.au/fire-information/fires-near-me",
    "link_text": "View more",
    "latitude": "-32.170154571",
    "longitude": "150.111602783",
    "region": "nsw",
    "time_of_call": "28 Dec 2024 11:37:00",
    "event_type": "burnt area",
    "status": "Under control",
    "status_description": "",
    "status_icon": "/sites/default/files/alert-svgs/narrow%20black%20yellow%20triangle.svg",
    "status_filter_label": "Active",
    "alert_level": "Advice",
    "location": "366-370 NEVERFAIL RD, MERRIWA 2329",
    "council_area": "Upper Hunter",
    "type": "Grass Fire",
    "type_description": "",
    "type_icon": "/sites/default/files/incident-type-svgs/fire_1_0_5.svg",
    "fire": "Yes",
    "size": "50 ha",
    "responsible_agency": "Rural Fire Service",
    "updated": "28 Dec 2024 11:37"
  },
  {
    "title": "WARKTON RD, COONABARABRAN",
    "id": "https___incidents_rfs_nsw_gov_au_api_v1_incidents_581719",
    "link": "http://www.rfs.nsw.gov.au/fire-information/fires-near-me",
    "link_text": "View more",
    "latitude": "-31.3756885519999",
    "longitude": "149.174011231",
    "region": "nsw",
    "time_of_call": "28 Dec 2024 15:45:00",
    "event_type": "burnt area",
    "status": "Under control",
    "alert_level": "Not Applicable",
    "location": "798 WARKTON RD, COONABARABRAN 2357",
    "council_area": "Warrumbungle",
    "type": "Bush Fire",
    "type_description": "",
    "type_icon": "/sites/default/files/incident-type-svgs/fire_1_0_2.svg",
    "fire": "Yes",
    "size": "0 ha",
    "responsible_agency": "Rural Fire Service",
    "updated": "28 Dec 2024 15:45"
  },
  {
    "title": "ATTUNGA ",
    "id": "https___incidents_rfs_nsw_gov_au_api_v1_incidents_581765",
    "link": "http://www.rfs.nsw.gov.au/fire-information/fires-near-me",
    "link_text": "View more",
    "latitude": "-30.9419199879999",
    "longitude": "150.940224059",
    "region": "nsw",
    "time_of_call": "28 Dec 2024 17:34:00",
    "event_type": "burnt area",
    "status": "Being controlled",
    "status_description": "",
    "status_icon": "/sites/default/files/alert-svgs/narrow%20black%20yellow%20triangle.svg",
    "status_filter_label": "Active",
    "alert_level": "Advice",
    "location": "ATTUNGA STATE FOREST INLET RD, ATTUNGA 2345",
    "council_area": "Tamworth",
    "type": "Bush Fire",
    "type_description": "",
    "type_icon": "/sites/default/files/incident-type-svgs/fire_1_0_2.svg",
    "fire": "Yes",
    "size": "25 ha",
    "responsible_agency": "Rural Fire Service",
    "updated": "28 Dec 2024 17:34"
  },
  {
    "title": "SCOTTS MAIN RANGE RD",
    "id": "https___incidents_rfs_nsw_gov_au_api_v1_incidents_581770",
    "link": "http://www.rfs.nsw.gov.au/fire-information/fires-near-me",
    "link_text": "View more",
    "latitude": "-34.028442082",
    "longitude": "150.381159782",
    "region": "nsw",
    "time_of_call": "28 Dec 2024 14:48:00",
    "event_type": "burnt area",
    "status": "Being controlled",
    "status_description": "",
    "status_icon": "/sites/default/files/alert-svgs/narrow%20black%20yellow%20triangle.svg",
    "status_filter_label": "Active",
    "alert_level": "Advice",
    "location": "LACEY CREEK FIRE SCOTTS MAIN RANGE RD, BLUE MOUNTAINS NATIONAL PARK 2790",
    "council_area": "Wollondilly",
    "type": "Bush Fire",
    "type_description": "",
    "type_icon": "/sites/default/files/incident-type-svgs/fire_1_0_2.svg",
    "fire": "Yes",
    "size": "0 ha",
    "responsible_agency": "NSW National Parks and Wildlife Service",
    "updated": "28 Dec 2024 14:48"
  },
  {
    "title": "NORRIES RD, BUNYAH",
    "id": "https___incidents_rfs_nsw_gov_au_api_v1_incidents_581777",
    "link": "http://www.rfs.nsw.gov.au/fire-information/fires-near-me",
    "link_text": "View more",
    "latitude": "-32.173927308",
    "longitude": "152.192321777",
    "region": "nsw",
    "time_of_call": "28 Dec 2024 14:06:00",
    "event_type": "burnt area",
    "status": "Under control",
    "status_description": "",
    "status_icon": "/sites/default/files/alert-svgs/narrow%20black%20yellow%20triangle.svg",
    "status_filter_label": "Active",
    "alert_level": "Advice",
    "location": "NORRIES RD, BUNYAH 2429",
    "council_area": "Mid-Coast",
    "type": "Bush Fire",
    "type_description": "",
    "type_icon": "/sites/default/files/incident-type-svgs/fire_1_0_2.svg",
    "fire": "Yes",
    "size": "0 ha",
    "responsible_agency": "Rural Fire Service",
    "updated": "28 Dec 2024 14:06"
  },
  {
    "title": "MUNYABLA MUNYAPLAH RD, RYAN",
    "id": "https___incidents_rfs_nsw_gov_au_api_v1_incidents_581789",
    "link": "http://www.rfs.nsw.gov.au/fire-information/fires-near-me",
    "link_text": "View more",
    "latitude": "-35.516056061",
    "longitude": "146.869812012",
    "region": "nsw",
    "time_of_call": "28 Dec 2024 10:35:00",
    "event_type": "burnt area",
    "status": "Under control",
    "alert_level": "Not Applicable",
    "location": "565 MUNYABLA MUNYAPLAH RD, RYAN 2658",
    "council_area": "Lockhart",
    "type": "Haystack fire",
    "type_description": "",
    "type_icon": "/sites/default/files/incident-type-svgs/fire_1_0_6.svg",
    "fire": "Yes",
    "size": "0 ha",
    "responsible_agency": "Rural Fire Service",
    "updated": "28 Dec 2024 10:35"
  },
  {
    "title": "FROGS HOLLOW LANE, FROGS HOLLOW",
    "id": "https___incidents_rfs_nsw_gov_au_api_v1_incidents_581814",
    "link": "http://www.rfs.nsw.gov.au/fire-information/fires-near-me",
    "link_text": "View more",
    "latitude": "-36.753189087",
    "longitude": "149.83543396",
    "region": "nsw",
    "time_of_call": "27 Dec 2024 22:14:00",
    "event_type": "burnt area",
    "status": "Under control",
    "alert_level": "Not Applicable",
    "location": "293 FROGS HOLLOW LANE, FROGS HOLLOW 2550",
    "council_area": "Bega Valley",
    "type": "Assist Other Agency",
    "fire": "No",
    "size": "0 ha",
    "responsible_agency": "Rural Fire Service",
    "updated": "27 Dec 2024 22:14"
  },
  {
    "title": "WARRUMBUNGLES WAY, COONABARABRAN",
    "id": "https___incidents_rfs_nsw_gov_au_api_v1_incidents_581826",
    "link": "http://www.rfs.nsw.gov.au/fire-information/fires-near-me",
    "link_text": "View more",
    "latitude": "-31.398225785",
    "longitude": "149.327392578",
    "region": "nsw",
    "time_of_call": "28 Dec 2024 15:42:00",
    "event_type": "burnt area",
    "status": "Under control",
    "status_description": "",
    "status_icon": "/sites/default/files/alert-svgs/narrow%20black%20yellow%20triangle.svg",
    "status_filter_label": "Active",
    "alert_level": "Advice",
    "location": "6051 WARRUMBUNGLES WAY, COONABARABRAN 2357",
    "council_area": "Warrumbungle",
    "type": "Bush Fire",
    "type_description": "",
    "type_icon": "/sites/default/files/incident-type-svgs/fire_1_0_2.svg",
    "fire": "Yes",
    "size": "0 ha",
    "responsible_agency": "Rural Fire Service",
    "updated": "28 Dec 2024 15:42"
  },
  {
    "title": "JERILDERIE RD, HAY SOUTH",
    "id": "https___incidents_rfs_nsw_gov_au_api_v1_incidents_581848",
    "link": "http://www.rfs.nsw.gov.au/fire-information/fires-near-me",
    "link_text": "View more",
    "latitude": "-34.6779937749999",
    "longitude": "145.049102783",
    "region": "nsw",
    "time_of_call": "28 Dec 2024 16:24:00",
    "event_type": "burnt area",
    "status": "Under control",
    "alert_level": "Not Applicable",
    "location": "JERILDERIE RD, HAY SOUTH 2711",
    "council_area": "Hay",
    "type": "Haystack fire",
    "type_description": "",
    "type_icon": "/sites/default/files/incident-type-svgs/fire_1_0_6.svg",
    "fire": "Yes",
    "size": "0 ha",
    "responsible_agency": "Rural Fire Service",
    "updated": "28 Dec 2024 16:24"
  },
  {
    "title": "Yarrowitch Trail",
    "id": "https___incidents_rfs_nsw_gov_au_api_v1_incidents_581857",
    "link": "http://www.rfs.nsw.gov.au/fire-information/fires-near-me",
    "link_text": "View more",
    "latitude": "-31.099465557",
    "longitude": "152.243213653",
    "region": "nsw",
    "time_of_call": "28 Dec 2024 15:47:00",
    "event_type": "burnt area",
    "status": "Being controlled",
    "alert_level": "Not Applicable",
    "location": "Oxley Wild Rivers National Park",
    "council_area": "Walcha",
    "type": "Bush Fire",
    "type_description": "",
    "type_icon": "/sites/default/files/incident-type-svgs/fire_1_0_2.svg",
    "fire": "Yes",
    "size": "1 ha",
    "responsible_agency": "NSW National Parks and Wildlife Service",
    "updated": "28 Dec 2024 15:47"
  },
  {
    "title": "OGUNBIL RD, DUNGOWAN",
    "id": "https___incidents_rfs_nsw_gov_au_api_v1_incidents_581874",
    "link": "http://www.rfs.nsw.gov.au/fire-information/fires-near-me",
    "link_text": "View more",
    "latitude": "-31.2198142999999",
    "longitude": "151.141738892",
    "region": "nsw",
    "time_of_call": "28 Dec 2024 17:17:00",
    "event_type": "burnt area",
    "status": "Being controlled",
    "status_description": "",
    "status_icon": "/sites/default/files/alert-svgs/narrow%20black%20yellow%20triangle.svg",
    "status_filter_label": "Active",
    "alert_level": "Advice",
    "location": "KILLARNEY 219 OGUNBIL RD, DUNGOWAN 2340",
    "council_area": "Tamworth",
    "type": "Grass Fire",
    "type_description": "",
    "type_icon": "/sites/default/files/incident-type-svgs/fire_1_0_5.svg",
    "fire": "Yes",
    "size": "206 ha",
    "major_fire_update_as_at_28_dec_2024_3:03pm": "<a href='http://www.rfs.nsw.gov.au/fire-information/major-fire-updates/mfu?id=12127' target='_blank'> More information</a>",
    "responsible_agency": "Rural Fire Service",
    "updated": "28 Dec 2024 17:17"
  },
  {
    "title": "TARRANTS GAP RD, WYANGALA",
    "id": "https___incidents_rfs_nsw_gov_au_api_v1_incidents_581878",
    "link": "http://www.rfs.nsw.gov.au/fire-information/fires-near-me",
    "link_text": "View more",
    "latitude": "-34.050938475",
    "longitude": "148.974343299",
    "region": "nsw",
    "time_of_call": "28 Dec 2024 15:55:00",
    "event_type": "burnt area",
    "status": "Under control",
    "status_description": "",
    "status_icon": "/sites/default/files/alert-svgs/narrow%20black%20yellow%20triangle.svg",
    "status_filter_label": "Active",
    "alert_level": "Advice",
    "location": "TARRANTS GAP RD, WYANGALA 2808",
    "council_area": "Hilltops",
    "type": "Bush Fire",
    "type_description": "",
    "type_icon": "/sites/default/files/incident-type-svgs/fire_1_0_2.svg",
    "fire": "Yes",
    "size": "5 ha",
    "responsible_agency": "Rural Fire Service",
    "updated": "28 Dec 2024 15:55"
  },
  {
    "title": "OXLEY HWY, LONG FLAT",
    "id": "https___incidents_rfs_nsw_gov_au_api_v1_incidents_581879",
    "link": "http://www.rfs.nsw.gov.au/fire-information/fires-near-me",
    "link_text": "View more",
    "latitude": "-31.4400177009999",
    "longitude": "152.502929687",
    "region": "nsw",
    "time_of_call": "28 Dec 2024 13:22:00",
    "event_type": "burnt area",
    "status": "Under control",
    "alert_level": "Not Applicable",
    "location": "OXLEY HWY, LONG FLAT 2446",
    "council_area": "Port Macquarie-Hastings",
    "type": "MVA/Transport",
    "type_description": "",
    "type_icon": "/sites/default/files/incident-type-svgs/car-0_0.svg",
    "fire": "No",
    "size": "0 ha",
    "responsible_agency": "Rural Fire Service",
    "updated": "28 Dec 2024 13:22"
  },
  {
    "title": "TWEED COAST RD, WOOYUNG",
    "id": "https___incidents_rfs_nsw_gov_au_api_v1_incidents_581883",
    "link": "http://www.rfs.nsw.gov.au/fire-information/fires-near-me",
    "link_text": "View more",
    "latitude": "-28.4296092989999",
    "longitude": "153.558227539",
    "region": "nsw",
    "time_of_call": "28 Dec 2024 13:49:00",
    "event_type": "burnt area",
    "status": "Under control",
    "status_description": "",
    "status_icon": "/sites/default/files/alert-svgs/narrow%20black%20yellow%20triangle.svg",
    "status_filter_label": "Active",
    "alert_level": "Advice",
    "location": "TWEED COAST RD, WOOYUNG 2483",
    "council_area": "Tweed",
    "type": "Grass Fire",
    "type_description": "",
    "type_icon": "/sites/default/files/incident-type-svgs/fire_1_0_5.svg",
    "fire": "Yes",
    "size": "0 ha",
    "responsible_agency": "Rural Fire Service",
    "updated": "28 Dec 2024 13:49"
  },
  {
    "title": "GWYDIRFIELD RD, MOREE",
    "id": "https___incidents_rfs_nsw_gov_au_api_v1_incidents_581885",
    "link": "http://www.rfs.nsw.gov.au/fire-information/fires-near-me",
    "link_text": "View more",
    "latitude": "-29.441190719",
    "longitude": "149.868774414",
    "region": "nsw",
    "time_of_call": "28 Dec 2024 17:11:00",
    "event_type": "burnt area",
    "status": "Under control",
    "status_description": "",
    "status_icon": "/sites/default/files/alert-svgs/narrow%20black%20yellow%20triangle.svg",
    "status_filter_label": "Active",
    "alert_level": "Advice",
    "location": "GWYDIRFIELD RD, MOREE 2400",
    "council_area": "Moree Plains",
    "type": "Grass Fire",
    "type_description": "",
    "type_icon": "/sites/default/files/incident-type-svgs/fire_1_0_5.svg",
    "fire": "Yes",
    "size": "0 ha",
    "responsible_agency": "Rural Fire Service",
    "updated": "28 Dec 2024 17:11"
  },
  {
    "title": "BOX FOREST RD, KINGSTOWN",
    "id": "https___incidents_rfs_nsw_gov_au_api_v1_incidents_581887",
    "link": "http://www.rfs.nsw.gov.au/fire-information/fires-near-me",
    "link_text": "View more",
    "latitude": "-30.441066878",
    "longitude": "151.082868571",
    "region": "nsw",
    "time_of_call": "28 Dec 2024 15:53:00",
    "event_type": "burnt area",
    "status": "Being controlled",
    "status_description": "",
    "status_icon": "/sites/default/files/alert-svgs/narrow%20black%20yellow%20triangle.svg",
    "status_filter_label": "Active",
    "alert_level": "Advice",
    "location": "ALLAWAH 1326 BOX FOREST RD, KINGSTOWN 2358",
    "council_area": "Uralla",
    "type": "Bush Fire",
    "type_description": "",
    "type_icon": "/sites/default/files/incident-type-svgs/fire_1_0_2.svg",
    "fire": "Yes",
    "size": "86 ha",
    "responsible_agency": "Rural Fire Service",
    "updated": "28 Dec 2024 15:53"
  },
  {
    "title": "SANDY CREEK RD, SANDY CREEK",
    "id": "https___incidents_rfs_nsw_gov_au_api_v1_incidents_581893",
    "link": "http://www.rfs.nsw.gov.au/fire-information/fires-near-me",
    "link_text": "View more",
    "latitude": "-31.797344208",
    "longitude": "150.957183837",
    "region": "nsw",
    "time_of_call": "28 Dec 2024 16:42:00",
    "event_type": "burnt area",
    "status": "Not yet controlled",
    "status_description": "",
    "status_icon": "/sites/default/files/alert-svgs/narrow%20black%20yellow%20triangle.svg",
    "status_filter_label": "Active",
    "alert_level": "Advice",
    "location": "SANDY CREEK RD, SANDY CREEK 2338",
    "council_area": "Upper Hunter",
    "type": "Bush Fire",
    "type_description": "",
    "type_icon": "/sites/default/files/incident-type-svgs/fire_1_0_2.svg",
    "fire": "Yes",
    "size": "0 ha",
    "responsible_agency": "Rural Fire Service",
    "updated": "28 Dec 2024 16:42"
  },
  {
    "title": "WARRABAH RD, WARRABAH",
    "id": "https___incidents_rfs_nsw_gov_au_api_v1_incidents_581895",
    "link": "http://www.rfs.nsw.gov.au/fire-information/fires-near-me",
    "link_text": "View more",
    "latitude": "-30.5229936979999",
    "longitude": "151.050201429",
    "region": "nsw",
    "time_of_call": "28 Dec 2024 17:37:00",
    "event_type": "burnt area",
    "status": "Being controlled",
    "status_description": "",
    "status_icon": "/sites/default/files/alert-svgs/narrow%20black%20yellow%20triangle.svg",
    "status_filter_label": "Active",
    "alert_level": "Advice",
    "location": "WARRABAH RD, WARRABAH 2346",
    "council_area": "Tamworth",
    "type": "Bush Fire",
    "type_description": "",
    "type_icon": "/sites/default/files/incident-type-svgs/fire_1_0_2.svg",
    "fire": "Yes",
    "size": "78 ha",
    "responsible_agency": "Rural Fire Service",
    "updated": "28 Dec 2024 17:37"
  },
  {
    "title": "BAERAMI RANGE",
    "id": "https___incidents_rfs_nsw_gov_au_api_v1_incidents_581898",
    "link": "http://www.rfs.nsw.gov.au/fire-information/fires-near-me",
    "link_text": "View more",
    "latitude": "-32.6303037169999",
    "longitude": "150.588908673",
    "region": "nsw",
    "time_of_call": "28 Dec 2024 16:16:00",
    "event_type": "burnt area",
    "status": "Not yet controlled",
    "status_description": "",
    "status_icon": "/sites/default/files/alert-svgs/narrow%20black%20yellow%20triangle.svg",
    "status_filter_label": "Active",
    "alert_level": "Advice",
    "location": "MARTINDALE RD, MARTINDALE 2328",
    "council_area": "Muswellbrook",
    "type": "Bush Fire",
    "type_description": "",
    "type_icon": "/sites/default/files/incident-type-svgs/fire_1_0_2.svg",
    "fire": "Yes",
    "size": "0 ha",
    "responsible_agency": "Rural Fire Service",
    "updated": "28 Dec 2024 16:16"
  },
  {
    "title": "TOMBOYE RD, TOMBOYE",
    "id": "https___incidents_rfs_nsw_gov_au_api_v1_incidents_581901",
    "link": "http://www.rfs.nsw.gov.au/fire-information/fires-near-me",
    "link_text": "View more",
    "latitude": "-35.26385498",
    "longitude": "149.913909912",
    "region": "nsw",
    "time_of_call": "28 Dec 2024 15:22:00",
    "event_type": "burnt area",
    "status": "Under control",
    "status_description": "",
    "status_icon": "/sites/default/files/alert-svgs/narrow%20black%20yellow%20triangle.svg",
    "status_filter_label": "Active",
    "alert_level": "Advice",
    "location": "40 TOMBOYE RD, TOMBOYE 2622",
    "council_area": "Queanbeyan-Palerang",
    "type": "Grass Fire",
    "type_description": "",
    "type_icon": "/sites/default/files/incident-type-svgs/fire_1_0_5.svg",
    "fire": "Yes",
    "size": "4 ha",
    "responsible_agency": "Rural Fire Service",
    "updated": "28 Dec 2024 15:22"
  },
  {
    "title": "TOURLES RD, LITTLE JACKS CREEK",
    "id": "https___incidents_rfs_nsw_gov_au_api_v1_incidents_581909",
    "link": "http://www.rfs.nsw.gov.au/fire-information/fires-near-me",
    "link_text": "View more",
    "latitude": "-31.781564713",
    "longitude": "150.519958496",
    "region": "nsw",
    "time_of_call": "28 Dec 2024 16:12:00",
    "event_type": "burnt area",
    "status": "Not yet controlled",
    "status_description": "",
    "status_icon": "/sites/default/files/alert-svgs/narrow%20black%20yellow%20triangle.svg",
    "status_filter_label": "Active",
    "alert_level": "Advice",
    "location": "100 TOURLES RD, LITTLE JACKS CREEK 2339",
    "council_area": "Liverpool Plains",
    "type": "Bush Fire",
    "type_description": "",
    "type_icon": "/sites/default/files/incident-type-svgs/fire_1_0_2.svg",
    "fire": "Yes",
    "size": "0 ha",
    "responsible_agency": "Rural Fire Service",
    "updated": "28 Dec 2024 16:12"
  },
  {
    "title": "ROSENEATH RD, WATSONS CREEK",
    "id": "https___incidents_rfs_nsw_gov_au_api_v1_incidents_581912",
    "link": "http://www.rfs.nsw.gov.au/fire-information/fires-near-me",
    "link_text": "View more",
    "latitude": "-30.684705735",
    "longitude": "150.96572876",
    "region": "nsw",
    "time_of_call": "28 Dec 2024 17:37:00",
    "event_type": "burnt area",
    "status": "Being controlled",
    "status_description": "",
    "status_icon": "/sites/default/files/alert-svgs/narrow%20black%20yellow%20triangle.svg",
    "status_filter_label": "Active",
    "alert_level": "Advice",
    "location": "ROSENEATH RD, WATSONS CREEK 2355",
    "council_area": "Tamworth",
    "type": "Bush Fire",
    "type_description": "",
    "type_icon": "/sites/default/files/incident-type-svgs/fire_1_0_2.svg",
    "fire": "Yes",
    "size": "0 ha",
    "responsible_agency": "Rural Fire Service",
    "updated": "28 Dec 2024 17:37"
  },
  {
    "title": "MIDDLEBROOK RD, MIDDLE BROOK",
    "id": "https___incidents_rfs_nsw_gov_au_api_v1_incidents_581914",
    "link": "http://www.rfs.nsw.gov.au/fire-information/fires-near-me",
    "link_text": "View more",
    "latitude": "-31.9339523309999",
    "longitude": "150.802398682",
    "region": "nsw",
    "time_of_call": "28 Dec 2024 16:25:00",
    "event_type": "burnt area",
    "status": "Under control",
    "status_description": "",
    "status_icon": "/sites/default/files/alert-svgs/narrow%20black%20yellow%20triangle.svg",
    "status_filter_label": "Active",
    "alert_level": "Advice",
    "location": "MIDDLEBROOK RD, MIDDLE BROOK 2337",
    "council_area": "Upper Hunter",
    "type": "Bush Fire",
    "type_description": "",
    "type_icon": "/sites/default/files/incident-type-svgs/fire_1_0_2.svg",
    "fire": "Yes",
    "size": "0 ha",
    "responsible_agency": "Rural Fire Service",
    "updated": "28 Dec 2024 16:25"
  },
  {
    "title": "WARATAH RD, WARRIMOO",
    "id": "https___incidents_rfs_nsw_gov_au_api_v1_incidents_581921",
    "link": "http://www.rfs.nsw.gov.au/fire-information/fires-near-me",
    "link_text": "View more",
    "latitude": "-33.719825745",
    "longitude": "150.592941284",
    "region": "nsw",
    "time_of_call": "28 Dec 2024 16:07:00",
    "event_type": "burnt area",
    "status": "Under control",
    "status_description": "",
    "status_icon": "/sites/default/files/alert-svgs/narrow%20black%20yellow%20triangle.svg",
    "status_filter_label": "Active",
    "alert_level": "Advice",
    "location": "27 WARATAH RD, WARRIMOO 2774",
    "council_area": "Blue Mountains",
    "type": "Grass Fire",
    "type_description": "",
    "type_icon": "/sites/default/files/incident-type-svgs/fire_1_0_5.svg",
    "fire": "Yes",
    "size": "0 ha",
    "responsible_agency": "Rural Fire Service",
    "updated": "28 Dec 2024 16:07"
  },
  {
    "title": "SIBLEY RD, GUNDAROO",
    "id": "https___incidents_rfs_nsw_gov_au_api_v1_incidents_581927",
    "link": "http://www.rfs.nsw.gov.au/fire-information/fires-near-me",
    "link_text": "View more",
    "latitude": "-35.015888214",
    "longitude": "149.240036011",
    "region": "nsw",
    "time_of_call": "28 Dec 2024 17:42:00",
    "event_type": "burnt area",
    "status": "Under control",
    "status_description": "",
    "status_icon": "/sites/default/files/alert-svgs/narrow%20black%20yellow%20triangle.svg",
    "status_filter_label": "Active",
    "alert_level": "Advice",
    "location": "SIBLEY RD, GUNDAROO 2620",
    "council_area": "Yass Valley",
    "type": "Grass Fire",
    "type_description": "",
    "type_icon": "/sites/default/files/incident-type-svgs/fire_1_0_5.svg",
    "fire": "Yes",
    "size": "0 ha",
    "responsible_agency": "Rural Fire Service",
    "updated": "28 Dec 2024 17:42"
  },
  {
    "title": "PADDYS FLAT RD, TABULAM",
    "id": "https___incidents_rfs_nsw_gov_au_api_v1_incidents_581930",
    "link": "http://www.rfs.nsw.gov.au/fire-information/fires-near-me",
    "link_text": "View more",
    "latitude": "-28.729970932",
    "longitude": "152.37991333",
    "region": "nsw",
    "time_of_call": "28 Dec 2024 17:03:00",
    "event_type": "burnt area",
    "status": "Responding",
    "alert_level": "Not Applicable",
    "location": "CURRAWINYA 2575 PADDYS FLAT RD, TABULAM 2469",
    "council_area": "Tenterfield",
    "type": "Bush Fire",
    "type_description": "",
    "type_icon": "/sites/default/files/incident-type-svgs/fire_1_0_2.svg",
    "fire": "Yes",
    "size": "0 ha",
    "responsible_agency": "Rural Fire Service",
    "updated": "28 Dec 2024 17:03"
  },
  {
    "title": "Green St, West Tamworth",
    "id": "https___incidents_rfs_nsw_gov_au_api_v1_incidents_581931",
    "link": "http://www.rfs.nsw.gov.au/fire-information/fires-near-me",
    "link_text": "View more",
    "latitude": "-31.1091999999999",
    "longitude": "150.894516",
    "region": "nsw",
    "time_of_call": "28 Dec 2024 17:14:00",
    "event_type": "burnt area",
    "status": "Being controlled",
    "status_description": "",
    "status_icon": "/sites/default/files/alert-svgs/narrow%20black%20yellow%20triangle.svg",
    "status_filter_label": "Active",
    "alert_level": "Advice",
    "location": "Green St, West Tamworth, NSW 2340",
    "council_area": "Tamworth",
    "type": "Grass Fire",
    "type_description": "",
    "type_icon": "/sites/default/files/incident-type-svgs/fire_1_0_5.svg",
    "fire": "Yes",
    "size": "0 ha",
    "responsible_agency": "Fire and Rescue NSW",
    "updated": "28 Dec 2024 17:14"
  },
  {
    "title": "WARRENA RD, COONAMBLE",
    "id": "https___incidents_rfs_nsw_gov_au_api_v1_incidents_581932",
    "link": "http://www.rfs.nsw.gov.au/fire-information/fires-near-me",
    "link_text": "View more",
    "latitude": "-31.1463451879999",
    "longitude": "148.545455933",
    "region": "nsw",
    "time_of_call": "28 Dec 2024 17:18:00",
    "event_type": "burnt area",
    "status": "Being controlled",
    "status_description": "",
    "status_icon": "/sites/default/files/alert-svgs/narrow%20black%20yellow%20triangle.svg",
    "status_filter_label": "Active",
    "alert_level": "Advice",
    "location": "WILLOW DOWNS 1957 WARRENA RD, COONAMBLE 2829",
    "council_area": "Coonamble",
    "type": "Grass Fire",
    "type_description": "",
    "type_icon": "/sites/default/files/incident-type-svgs/fire_1_0_5.svg",
    "fire": "Yes",
    "size": "0 ha",
    "responsible_agency": "Rural Fire Service",
    "updated": "28 Dec 2024 17:18"
  },
  {
    "title": "TWENTY THIRD AV, WEST HOXTON",
    "id": "https___incidents_rfs_nsw_gov_au_api_v1_incidents_581934",
    "link": "http://www.rfs.nsw.gov.au/fire-information/fires-near-me",
    "link_text": "View more",
    "latitude": "-33.9294013969999",
    "longitude": "150.827713013",
    "region": "nsw",
    "time_of_call": "28 Dec 2024 17:16:00",
    "event_type": "burnt area",
    "status": "Responding",
    "alert_level": "Not Applicable",
    "location": "TWENTY THIRD AV, WEST HOXTON 2171",
    "council_area": "Liverpool",
    "type": "Bush Fire",
    "type_description": "",
    "type_icon": "/sites/default/files/incident-type-svgs/fire_1_0_2.svg",
    "fire": "Yes",
    "size": "0 ha",
    "responsible_agency": "Rural Fire Service",
    "updated": "28 Dec 2024 17:16"
  },
  {
    "title": "LAKE BURRENDONG",
    "id": "https___incidents_rfs_nsw_gov_au_api_v1_incidents_581935",
    "link": "http://www.rfs.nsw.gov.au/fire-information/fires-near-me",
    "link_text": "View more",
    "latitude": "-32.679477692",
    "longitude": "149.135177612",
    "region": "nsw",
    "time_of_call": "28 Dec 2024 17:21:00",
    "event_type": "burnt area",
    "status": "Responding",
    "alert_level": "Not Applicable",
    "location": "LAKE BURRENDONG 2820",
    "council_area": "Dubbo Regional",
    "type": "Other",
    "type_description": "",
    "type_icon": "/sites/default/files/incident-type-svgs/incident-other.svg",
    "fire": "Yes",
    "size": "0 ha",
    "responsible_agency": "Rural Fire Service",
    "updated": "28 Dec 2024 17:21"
  },
  {
    "title": "OAKHAMPTON RD, RED HILL",
    "id": "https___incidents_rfs_nsw_gov_au_api_v1_incidents_581936",
    "link": "http://www.rfs.nsw.gov.au/fire-information/fires-near-me",
    "link_text": "View more",
    "latitude": "-30.497037888",
    "longitude": "150.623718262",
    "region": "nsw",
    "time_of_call": "28 Dec 2024 17:37:00",
    "event_type": "burnt area",
    "status": "Responding",
    "alert_level": "Not Applicable",
    "location": "OAKHAMPTON RD, RED HILL 2347",
    "council_area": "Tamworth",
    "type": "Grass Fire",
    "type_description": "",
    "type_icon": "/sites/default/files/incident-type-svgs/fire_1_0_5.svg",
    "fire": "Yes",
    "size": "0 ha",
    "responsible_agency": "Rural Fire Service",
    "updated": "28 Dec 2024 17:37"
  },
  {
    "title": "PAYNTERS SIDING RD, NARRANDERA",
    "id": "https___incidents_rfs_nsw_gov_au_api_v1_incidents_581937",
    "link": "http://www.rfs.nsw.gov.au/fire-information/fires-near-me",
    "link_text": "View more",
    "latitude": "-34.713451386",
    "longitude": "146.52961731",
    "region": "nsw",
    "time_of_call": "28 Dec 2024 17:31:00",
    "event_type": "burnt area",
    "status": "Responding",
    "alert_level": "Not Applicable",
    "location": "PAYNTERS SIDING RD, NARRANDERA 2700",
    "council_area": "Narrandera",
    "type": "Grass Fire",
    "type_description": "",
    "type_icon": "/sites/default/files/incident-type-svgs/fire_1_0_5.svg",
    "fire": "Yes",
    "size": "0 ha",
    "responsible_agency": "Rural Fire Service",
    "updated": "28 Dec 2024 17:31"
  },
  {
    "title": "Dingo Creek",
    "id": "https___incidents_rfs_nsw_gov_au_api_v1_incidents_581939",
    "link": "http://www.rfs.nsw.gov.au/fire-information/fires-near-me",
    "link_text": "View more",
    "latitude": "-33.125476837",
    "longitude": "150.387039185",
    "region": "nsw",
    "time_of_call": "28 Dec 2024 17:44:00",
    "event_type": "burnt area",
    "status": "Not yet controlled",
    "status_description": "",
    "status_icon": "/sites/default/files/alert-svgs/narrow%20black%20yellow%20triangle.svg",
    "status_filter_label": "Active",
    "alert_level": "Advice",
    "location": "Wollemi National Park",
    "council_area": "Lithgow",
    "type": "Bush Fire",
    "type_description": "",
    "type_icon": "/sites/default/files/incident-type-svgs/fire_1_0_2.svg",
    "fire": "Yes",
    "size": "0 ha",
    "responsible_agency": "NSW National Parks and Wildlife Service",
    "updated": "28 Dec 2024 17:44"
  },
  {
    "title": "WATERCOURSE RD, MOREE",
    "id": "https___incidents_rfs_nsw_gov_au_api_v1_incidents_581940",
    "link": "http://www.rfs.nsw.gov.au/fire-information/fires-near-me",
    "link_text": "View more",
    "latitude": "-29.4102706909999",
    "longitude": "149.501144409",
    "region": "nsw",
    "time_of_call": "28 Dec 2024 17:39:00",
    "event_type": "burnt area",
    "status": "Responding",
    "alert_level": "Not Applicable",
    "location": "WATERCOURSE RD, MOREE 2400",
    "council_area": "Moree Plains",
    "type": "Other",
    "type_description": "",
    "type_icon": "/sites/default/files/incident-type-svgs/incident-other.svg",
    "fire": "Yes",
    "size": "0 ha",
    "responsible_agency": "Rural Fire Service",
    "updated": "28 Dec 2024 17:39"
  },
  {
    "title": "Sussex St, West Tamworth",
    "id": "https___incidents_rfs_nsw_gov_au_api_v1_incidents_581942",
    "link": "http://www.rfs.nsw.gov.au/fire-information/fires-near-me",
    "link_text": "View more",
    "latitude": "-31.1091999999999",
    "longitude": "150.894516",
    "region": "nsw",
    "time_of_call": "28 Dec 2024 17:47:00",
    "event_type": "burnt area",
    "status": "Not yet controlled",
    "status_description": "",
    "status_icon": "/sites/default/files/alert-svgs/narrow%20black%20yellow%20triangle.svg",
    "status_filter_label": "Active",
    "alert_level": "Advice",
    "location": "Sussex St, West Tamworth, NSW 2340",
    "council_area": "Tamworth",
    "type": "Grass Fire",
    "type_description": "",
    "type_icon": "/sites/default/files/incident-type-svgs/fire_1_0_5.svg",
    "fire": "Yes",
    "size": "0 ha",
    "responsible_agency": "Fire and Rescue NSW",
    "updated": "28 Dec 2024 17:47"
  }
]
