[
  {
    "agency": "Ambulance",
    "alert_level": "",
    "event_type": "incident",
    "title": "AMBULANCE RESPONSE - O'CONNOR",
    "id": "076151-14122024",
    "latitude": "-35.256876",
    "longitude": "149.111857",
    "region": "act",
    "time_of_call": "14 Dec 2024 09:37:18",
    "status": "Resource Allocation Pending",
    "status_description": "",
    "status_icon": "/sites/default/files/type-ambulance-svgs/narrow%20ambulance%20blue-0_2.svg",
    "status_filter_label": "Resource Allocation Pending",
    "type": "AMBULANCE RESPONSE",
    "location": "O'CONNOR",
    "updated": "14 Dec 2024 10:49:23"
  },
  {
    "agency": "Ambulance",
    "alert_level": "",
    "event_type": "incident",
    "title": "SOUTHCARE RESPONSE - HUME",
    "id": "076164-14122024",
    "latitude": "-35.378629",
    "longitude": "149.171102",
    "region": "act",
    "time_of_call": "14 Dec 2024 10:45:28",
    "status": "On Scene",
    "status_description": "",
    "status_icon": "/sites/default/files/type-ambulance-svgs/narrow%20ambulance%20blue-0_1.svg",
    "status_filter_label": "On Scene",
    "type": "SOUTHCARE RESPONSE",
    "location": "HUME",
    "updated": "14 Dec 2024 12:46:04"
  },
  {
    "agency": "Ambulance",
    "alert_level": "",
    "event_type": "incident",
    "title": "AMBULANCE RESPONSE - PAGE",
    "id": "076180-14122024",
    "latitude": "-35.238051",
    "longitude": "149.050138",
    "region": "act",
    "time_of_call": "14 Dec 2024 12:07:22",
    "status": "On Scene",
    "status_description": "",
    "status_icon": "/sites/default/files/type-ambulance-svgs/narrow%20ambulance%20blue-0_1.svg",
    "status_filter_label": "On Scene",
    "type": "AMBULANCE RESPONSE",
    "location": "PAGE",
    "updated": "14 Dec 2024 14:14:17"
  },
  {
    "agency": "Ambulance",
    "alert_level": "",
    "event_type": "incident",
    "title": "AMBULANCE RESPONSE - GUNGAHLIN",
    "id": "076181-14122024",
    "latitude": "-35.184984",
    "longitude": "149.135062",
    "region": "act",
    "time_of_call": "14 Dec 2024 12:13:18",
    "status": "On Scene",
    "status_description": "",
    "status_icon": "/sites/default/files/type-ambulance-svgs/narrow%20ambulance%20blue-0_1.svg",
    "status_filter_label": "On Scene",
    "type": "AMBULANCE RESPONSE",
    "location": "GUNGAHLIN",
    "updated": "14 Dec 2024 14:42:12"
  },
  {
    "agency": "Ambulance",
    "alert_level": "",
    "event_type": "incident",
    "title": "AMBULANCE RESPONSE - CURTIN",
    "id": "076189-14122024",
    "latitude": "-35.326585",
    "longitude": "149.076856",
    "region": "act",
    "time_of_call": "14 Dec 2024 13:04:59",
    "status": "On Scene",
    "status_description": "",
    "status_icon": "/sites/default/files/type-ambulance-svgs/narrow%20ambulance%20blue-0_1.svg",
    "status_filter_label": "On Scene",
    "type": "AMBULANCE RESPONSE",
    "location": "CURTIN",
    "updated": "14 Dec 2024 14:35:58"
  },
  {
    "agency": "Ambulance",
    "alert_level": "",
    "event_type": "incident",
    "title": "MOTOR VEHICLE ACCIDENT - MAJURA",
    "id": "076190-14122024",
    "latitude": "-35.2163467407",
    "longitude": "149.1840667725",
    "region": "act",
    "time_of_call": "14 Dec 2024 13:05:28",
    "status": "On Scene",
    "status_description": "",
    "status_icon": "/sites/default/files/type-ambulance-svgs/narrow%20ambulance%20blue-0_1.svg",
    "status_filter_label": "On Scene",
    "type": "MOTOR VEHICLE ACCIDENT",
    "type_description": "",
    "type_icon": "",
    "location": "FEDERAL HIGHWAY, MAJURA ROAD, GUNGAHLIN, 0000",
    "updated": "14 Dec 2024 14:31:16"
  },
  {
    "agency": "Ambulance",
    "alert_level": "",
    "event_type": "incident",
    "title": "AMBULANCE RESPONSE - COOK",
    "id": "076194-14122024",
    "latitude": "-35.261055",
    "longitude": "149.064271",
    "region": "act",
    "time_of_call": "14 Dec 2024 13:29:03",
    "status": "On Scene",
    "status_description": "",
    "status_icon": "/sites/default/files/type-ambulance-svgs/narrow%20ambulance%20blue-0_1.svg",
    "status_filter_label": "On Scene",
    "type": "AMBULANCE RESPONSE",
    "location": "COOK",
    "updated": "14 Dec 2024 14:29:47"
  },
  {
    "agency": "Ambulance",
    "alert_level": "",
    "event_type": "incident",
    "title": "AMBULANCE RESPONSE - FARRER",
    "id": "076196-14122024",
    "latitude": "-35.377331",
    "longitude": "149.104586",
    "region": "act",
    "time_of_call": "14 Dec 2024 13:44:35",
    "status": "On Scene",
    "status_description": "",
    "status_icon": "/sites/default/files/type-ambulance-svgs/narrow%20ambulance%20blue-0_1.svg",
    "status_filter_label": "On Scene",
    "type": "AMBULANCE RESPONSE",
    "location": "FARRER",
    "updated": "14 Dec 2024 14:24:35"
  },
  {
    "agency": "Ambulance",
    "alert_level": "",
    "event_type": "incident",
    "title": "AMBULANCE RESPONSE - THROSBY",
    "id": "076197-14122024",
    "latitude": "-35.187595",
    "longitude": "149.161141",
    "region": "act",
    "time_of_call": "14 Dec 2024 13:59:07",
    "status": "Finished",
    "status_description": "",
    "status_icon": "/sites/default/files/type-ambulance-svgs/narrow%20ambulance%20triangle-0.svg",
    "status_filter_label": "Finished",
    "type": "AMBULANCE RESPONSE",
    "location": "THROSBY",
    "updated": "14 Dec 2024 14:42:16"
  },
  {
    "agency": "Ambulance",
    "alert_level": "",
    "event_type": "incident",
    "title": "AMBULANCE RESPONSE - WANNIASSA",
    "id": "076199-14122024",
    "latitude": "-35.399113",
    "longitude": "149.091978",
    "region": "act",
    "time_of_call": "14 Dec 2024 14:03:47",
    "status": "On Scene",
    "status_description": "",
    "status_icon": "/sites/default/files/type-ambulance-svgs/narrow%20ambulance%20blue-0_1.svg",
    "status_filter_label": "On Scene",
    "type": "AMBULANCE RESPONSE",
    "location": "WANNIASSA",
    "updated": "14 Dec 2024 14:40:16"
  },
  {
    "agency": "Ambulance",
    "alert_level": "",
    "event_type": "incident",
    "title": "AMBULANCE RESPONSE - PADDYS RIVER",
    "id": "076201-14122024",
    "latitude": "-35.444679",
    "longitude": "148.975963",
    "region": "act",
    "time_of_call": "14 Dec 2024 14:04:59",
    "status": "On Scene",
    "status_description": "",
    "status_icon": "/sites/default/files/type-ambulance-svgs/narrow%20ambulance%20blue-0_1.svg",
    "status_filter_label": "On Scene",
    "type": "AMBULANCE RESPONSE",
    "location": "PADDYS RIVER",
    "updated": "14 Dec 2024 14:49:47"
  },
  {
    "agency": "Ambulance",
    "alert_level": "",
    "event_type": "incident",
    "title": "AMBULANCE RESPONSE - GORDON",
    "id": "076202-14122024",
    "latitude": "-35.459685",
    "longitude": "149.084101",
    "region": "act",
    "time_of_call": "14 Dec 2024 14:17:07",
    "status": "Resource Allocation Pending",
    "status_description": "",
    "status_icon": "/sites/default/files/type-ambulance-svgs/narrow%20ambulance%20blue-0_2.svg",
    "status_filter_label": "Resource Allocation Pending",
    "type": "AMBULANCE RESPONSE",
    "location": "GORDON",
    "updated": "14 Dec 2024 14:20:11"
  },
  {
    "agency": "Ambulance",
    "alert_level": "",
    "event_type": "incident",
    "title": "PEDESTRIAN-PUSHBIKE-E-SCOOTER ACCIDENT - FYSHWICK",
    "id": "076203-14122024",
    "latitude": "-35.3150596619",
    "longitude": "149.1552581787",
    "region": "act",
    "time_of_call": "14 Dec 2024 14:25:34",
    "status": "On Scene",
    "status_description": "",
    "status_icon": "/sites/default/files/type-ambulance-svgs/narrow%20ambulance%20blue-0_1.svg",
    "status_filter_label": "On Scene",
    "type": "PEDESTRIAN-PUSHBIKE-E-SCOOTER ACCIDENT",
    "location": "EYRE STREET, BLUEBERRY STREET, KINGSTON, 2604",
    "updated": "14 Dec 2024 14:35:19"
  },
  {
    "agency": "Ambulance",
    "alert_level": "",
    "event_type": "incident",
    "title": "AMBULANCE RESPONSE - AMAROO",
    "id": "076204-14122024",
    "latitude": "-35.172039",
    "longitude": "149.129625",
    "region": "act",
    "time_of_call": "14 Dec 2024 14:29:23",
    "status": "On Scene",
    "status_description": "",
    "status_icon": "/sites/default/files/type-ambulance-svgs/narrow%20ambulance%20blue-0_1.svg",
    "status_filter_label": "On Scene",
    "type": "AMBULANCE RESPONSE",
    "location": "AMAROO",
    "updated": "14 Dec 2024 14:41:40"
  },
  {
    "agency": "Ambulance",
    "alert_level": "",
    "event_type": "incident",
    "title": "AMBULANCE RESPONSE - AINSLIE",
    "id": "076205-14122024",
    "latitude": "-35.262117",
    "longitude": "149.144037",
    "region": "act",
    "time_of_call": "14 Dec 2024 14:29:32",
    "status": "Resource Allocation Pending",
    "status_description": "",
    "status_icon": "/sites/default/files/type-ambulance-svgs/narrow%20ambulance%20blue-0_2.svg",
    "status_filter_label": "Resource Allocation Pending",
    "type": "AMBULANCE RESPONSE",
    "location": "AINSLIE",
    "updated": "14 Dec 2024 14:37:48"
  },
  {
    "agency": "Ambulance",
    "alert_level": "",
    "event_type": "incident",
    "title": "AMBULANCE RESPONSE - BONYTHON",
    "id": "076206-14122024",
    "latitude": "-35.435736",
    "longitude": "149.081053",
    "region": "act",
    "time_of_call": "14 Dec 2024 14:31:14",
    "status": "Resource Allocation Pending",
    "status_description": "",
    "status_icon": "/sites/default/files/type-ambulance-svgs/narrow%20ambulance%20blue-0_2.svg",
    "status_filter_label": "Resource Allocation Pending",
    "type": "AMBULANCE RESPONSE",
    "location": "BONYTHON",
    "updated": "14 Dec 2024 14:34:39"
  },
  {
    "agency": "Ambulance",
    "alert_level": "",
    "event_type": "incident",
    "title": "AMBULANCE RESPONSE - DICKSON",
    "id": "076207-14122024",
    "latitude": "-35.250784",
    "longitude": "149.142366",
    "region": "act",
    "time_of_call": "14 Dec 2024 14:38:58",
    "status": "Resource Allocation Pending",
    "status_description": "",
    "status_icon": "/sites/default/files/type-ambulance-svgs/narrow%20ambulance%20blue-0_2.svg",
    "status_filter_label": "Resource Allocation Pending",
    "type": "AMBULANCE RESPONSE",
    "location": "DICKSON",
    "updated": "14 Dec 2024 14:44:44"
  },
  {
    "agency": "Ambulance",
    "alert_level": "",
    "event_type": "incident",
    "title": "AMBULANCE RESPONSE - GRIFFITH",
    "id": "076208-14122024",
    "latitude": "-35.325773",
    "longitude": "149.133842",
    "region": "act",
    "time_of_call": "14 Dec 2024 14:40:39",
    "status": "Resource Allocation Pending",
    "status_description": "",
    "status_icon": "/sites/default/files/type-ambulance-svgs/narrow%20ambulance%20blue-0_2.svg",
    "status_filter_label": "Resource Allocation Pending",
    "type": "AMBULANCE RESPONSE",
    "location": "GRIFFITH",
    "updated": "14 Dec 2024 14:45:40"
  },
  {
    "agency": "Ambulance",
    "alert_level": "",
    "event_type": "incident",
    "title": "AMBULANCE RESPONSE - BELCONNEN",
    "id": "076209-14122024",
    "latitude": "-35.235936",
    "longitude": "149.066372",
    "region": "act",
    "time_of_call": "14 Dec 2024 14:43:23",
    "status": "Resource Allocation Pending",
    "status_description": "",
    "status_icon": "/sites/default/files/type-ambulance-svgs/narrow%20ambulance%20blue-0_2.svg",
    "status_filter_label": "Resource Allocation Pending",
    "type": "AMBULANCE RESPONSE",
    "location": "BELCONNEN",
    "updated": "14 Dec 2024 14:47:26"
  },
  {
    "agency": "Ambulance",
    "alert_level": "",
    "event_type": "incident",
    "title": "AMBULANCE RESPONSE - NGUNNAWAL",
    "id": "076210-14122024",
    "latitude": "-35.17365",
    "longitude": "149.112409",
    "region": "act",
    "time_of_call": "14 Dec 2024 14:49:45",
    "status": "Resource Allocation Pending",
    "status_description": "",
    "status_icon": "/sites/default/files/type-ambulance-svgs/narrow%20ambulance%20blue-0_2.svg",
    "status_filter_label": "Resource Allocation Pending",
    "type": "AMBULANCE RESPONSE",
    "location": "NGUNNAWAL",
    "updated": "14 Dec 2024 14:51:17"
  },
  {
    "title": "Toms Farm Creek",
    "id": "https___incidents_rfs_nsw_gov_au_api_v1_incidents_576477",
    "link": "http://www.rfs.nsw.gov.au/fire-information/fires-near-me",
    "link_text": "View more",
    "latitude": "-36.7932014469999",
    "longitude": "148.808441163",
    "region": "nsw",
    "time_of_call": "14 Dec 2024 10:15:00",
    "event_type": "burnt area",
    "status": "Under control",
    "status_description": "",
    "status_icon": "/sites/default/files/alert-svgs/narrow%20black%20yellow%20triangle.svg",
    "status_filter_label": "Active",
    "alert_level": "Advice",
    "location": "SETTLERS RD, CORROWONG 2633",
    "council_area": "Snowy Monaro",
    "type": "Bush Fire",
    "type_description": "",
    "type_icon": "/sites/default/files/incident-type-svgs/fire_1_0_2.svg",
    "fire": "Yes",
    "size": "140 ha",
    "responsible_agency": "NSW National Parks and Wildlife Service",
    "updated": "14 Dec 2024 10:15"
  },
  {
    "title": "LIMEBURNERS CREEK RD",
    "id": "https___incidents_rfs_nsw_gov_au_api_v1_incidents_578262",
    "link": "http://www.rfs.nsw.gov.au/fire-information/fires-near-me",
    "link_text": "View more",
    "latitude": "-32.608146667",
    "longitude": "151.810195923",
    "region": "nsw",
    "time_of_call": "13 Dec 2024 11:55:00",
    "event_type": "burnt area",
    "status": "Under control",
    "alert_level": "Not Applicable",
    "location": "GILMORE TRL LIMEBURNERS CREEK RD, CLARENCE TOWN 2321",
    "council_area": "Dungog",
    "type": "Bush Fire",
    "type_description": "",
    "type_icon": "/sites/default/files/incident-type-svgs/fire_1_0_2.svg",
    "fire": "Yes",
    "size": "0 ha",
    "responsible_agency": "NSW National Parks and Wildlife Service",
    "updated": "13 Dec 2024 11:55"
  },
  {
    "title": "WALLAGA LAKE RD, WALLAGA LAKE",
    "id": "https___incidents_rfs_nsw_gov_au_api_v1_incidents_578484",
    "link": "http://www.rfs.nsw.gov.au/fire-information/fires-near-me",
    "link_text": "View more",
    "latitude": "-36.3836593619999",
    "longitude": "150.068038941",
    "region": "nsw",
    "time_of_call": "13 Dec 2024 18:35:00",
    "event_type": "burnt area",
    "status": "Under control",
    "alert_level": "Planned Burn",
    "location": "769 WALLAGA LAKE RD, WALLAGA LAKE 2546",
    "council_area": "Bega Valley",
    "type": "Hazard Reduction",
    "type_description": "",
    "type_icon": "/sites/default/files/incident-type-svgs/haz-reduct-fire_1.svg",
    "fire": "Yes",
    "size": "0 ha",
    "responsible_agency": "Rural Fire Service",
    "updated": "13 Dec 2024 18:35"
  },
  {
    "title": "Albion Park Pile burn",
    "id": "https___incidents_rfs_nsw_gov_au_api_v1_incidents_578584",
    "link": "http://www.rfs.nsw.gov.au/fire-information/fires-near-me",
    "link_text": "View more",
    "latitude": "-34.6159515379999",
    "longitude": "150.733215332",
    "region": "nsw",
    "time_of_call": "14 Dec 2024 13:24:00",
    "event_type": "burnt area",
    "status": "Under control",
    "alert_level": "Planned Burn",
    "location": "210 STOCKYARD MOUNTAIN RD, YELLOW ROCK 2527",
    "council_area": "Kiama",
    "type": "Hazard Reduction",
    "type_description": "",
    "type_icon": "/sites/default/files/incident-type-svgs/haz-reduct-fire_1.svg",
    "fire": "Yes",
    "size": "0 ha",
    "responsible_agency": "Rural Fire Service",
    "updated": "14 Dec 2024 13:24"
  },
  {
    "title": "Godlee Lane HR",
    "id": "https___incidents_rfs_nsw_gov_au_api_v1_incidents_578609",
    "link": "http://www.rfs.nsw.gov.au/fire-information/fires-near-me",
    "link_text": "View more",
    "latitude": "-31.043205261",
    "longitude": "150.95362854",
    "region": "nsw",
    "time_of_call": "14 Dec 2024 02:01:00",
    "event_type": "burnt area",
    "status": "Under control",
    "alert_level": "Planned Burn",
    "location": "136 GODLEE LANE, DARUKA 2340",
    "council_area": "Tamworth",
    "type": "Hazard Reduction",
    "type_description": "",
    "type_icon": "/sites/default/files/incident-type-svgs/haz-reduct-fire_1.svg",
    "fire": "Yes",
    "size": "6 ha",
    "responsible_agency": "Rural Fire Service",
    "updated": "14 Dec 2024 02:01"
  },
  {
    "title": "WALBUNDRIE RD, CULCAIRN",
    "id": "https___incidents_rfs_nsw_gov_au_api_v1_incidents_578649",
    "link": "http://www.rfs.nsw.gov.au/fire-information/fires-near-me",
    "link_text": "View more",
    "latitude": "-35.666034698",
    "longitude": "146.963668823",
    "region": "nsw",
    "time_of_call": "14 Dec 2024 09:56:00",
    "event_type": "burnt area",
    "status": "Under control",
    "alert_level": "Not Applicable",
    "location": "WALBUNDRIE RD, CULCAIRN 2660",
    "council_area": "Greater Hume",
    "type": "Haystack fire",
    "type_description": "",
    "type_icon": "/sites/default/files/incident-type-svgs/fire_1_0_6.svg",
    "fire": "Yes",
    "size": "0 ha",
    "responsible_agency": "Rural Fire Service",
    "updated": "14 Dec 2024 09:56"
  },
  {
    "title": "Clarkes Road Fire",
    "id": "https___incidents_rfs_nsw_gov_au_api_v1_incidents_578666",
    "link": "http://www.rfs.nsw.gov.au/fire-information/fires-near-me",
    "link_text": "View more",
    "latitude": "-35.97864966",
    "longitude": "144.910908498",
    "region": "nsw",
    "time_of_call": "14 Dec 2024 09:46:00",
    "event_type": "burnt area",
    "status": "Under control",
    "status_description": "",
    "status_icon": "/sites/default/files/alert-svgs/narrow%20black%20yellow%20triangle.svg",
    "status_filter_label": "Active",
    "alert_level": "Advice",
    "location": "CLARKES RD, MOAMA 2731",
    "council_area": "Murray River",
    "type": "Bush Fire",
    "type_description": "",
    "type_icon": "/sites/default/files/incident-type-svgs/fire_1_0_2.svg",
    "fire": "Yes",
    "size": "21 ha",
    "responsible_agency": "NSW National Parks and Wildlife Service",
    "updated": "14 Dec 2024 09:46"
  },
  {
    "title": "BRITON COURT RD, STROUD",
    "id": "https___incidents_rfs_nsw_gov_au_api_v1_incidents_578720",
    "link": "http://www.rfs.nsw.gov.au/fire-information/fires-near-me",
    "link_text": "View more",
    "latitude": "-32.4127120969999",
    "longitude": "151.957611084",
    "region": "nsw",
    "time_of_call": "14 Dec 2024 02:00:00",
    "event_type": "burnt area",
    "status": "Under control",
    "alert_level": "Not Applicable",
    "location": "220 BRITON COURT RD, STROUD 2425",
    "council_area": "Mid-Coast",
    "type": "Burn off",
    "type_description": "",
    "type_icon": "/sites/default/files/incident-type-svgs/fire_1_0_1.svg",
    "fire": "Yes",
    "size": "0 ha",
    "responsible_agency": "Rural Fire Service",
    "updated": "14 Dec 2024 02:00"
  },
  {
    "title": "GURLEY ST, GURLEY",
    "id": "https___incidents_rfs_nsw_gov_au_api_v1_incidents_578733",
    "link": "http://www.rfs.nsw.gov.au/fire-information/fires-near-me",
    "link_text": "View more",
    "latitude": "-29.7351684569999",
    "longitude": "149.799377442",
    "region": "nsw",
    "time_of_call": "13 Dec 2024 20:14:00",
    "event_type": "burnt area",
    "status": "Under control",
    "alert_level": "Not Applicable",
    "location": "21 GURLEY ST, GURLEY 2398",
    "council_area": "Moree Plains",
    "type": "Structure Fire",
    "type_description": "",
    "type_icon": "/sites/default/files/incident-type-svgs/fire-building_2.svg",
    "fire": "Yes",
    "size": "0 ha",
    "responsible_agency": "Rural Fire Service",
    "updated": "13 Dec 2024 20:14"
  },
  {
    "title": "Range Rd",
    "id": "https___incidents_rfs_nsw_gov_au_api_v1_incidents_578756",
    "link": "http://www.rfs.nsw.gov.au/fire-information/fires-near-me",
    "link_text": "View more",
    "latitude": "-32.6231384279999",
    "longitude": "151.192886352",
    "region": "nsw",
    "time_of_call": "14 Dec 2024 13:46:00",
    "event_type": "burnt area",
    "status": "Being controlled",
    "status_description": "",
    "status_icon": "/sites/default/files/alert-svgs/narrow%20black%20yellow%20triangle.svg",
    "status_filter_label": "Active",
    "alert_level": "Advice",
    "location": "121 RANGE RD, WHITTINGHAM 2330",
    "council_area": "Singleton",
    "type": "Bush Fire",
    "type_description": "",
    "type_icon": "/sites/default/files/incident-type-svgs/fire_1_0_2.svg",
    "fire": "Yes",
    "size": "0 ha",
    "responsible_agency": "Rural Fire Service",
    "updated": "14 Dec 2024 13:46"
  },
  {
    "title": "KENYU RD, BOOROWA",
    "id": "https___incidents_rfs_nsw_gov_au_api_v1_incidents_578792",
    "link": "http://www.rfs.nsw.gov.au/fire-information/fires-near-me",
    "link_text": "View more",
    "latitude": "-34.2352485659999",
    "longitude": "148.758621216",
    "region": "nsw",
    "time_of_call": "13 Dec 2024 23:57:00",
    "event_type": "burnt area",
    "status": "Under control",
    "status_description": "",
    "status_icon": "/sites/default/files/alert-svgs/narrow%20black%20yellow%20triangle.svg",
    "status_filter_label": "Active",
    "alert_level": "Advice",
    "location": "ROWENA 2326 KENYU RD, BOOROWA 2586",
    "council_area": "Hilltops",
    "type": "Grass Fire",
    "type_description": "",
    "type_icon": "/sites/default/files/incident-type-svgs/fire_1_0_5.svg",
    "fire": "Yes",
    "size": "5 ha",
    "responsible_agency": "Rural Fire Service",
    "updated": "13 Dec 2024 23:57"
  },
  {
    "title": "HENRY LAWSON WAY, THUDDUNGRA",
    "id": "https___incidents_rfs_nsw_gov_au_api_v1_incidents_578793",
    "link": "http://www.rfs.nsw.gov.au/fire-information/fires-near-me",
    "link_text": "View more",
    "latitude": "-34.167476654",
    "longitude": "148.257003784",
    "region": "nsw",
    "time_of_call": "13 Dec 2024 23:58:00",
    "event_type": "burnt area",
    "status": "Under control",
    "status_description": "",
    "status_icon": "/sites/default/files/alert-svgs/narrow%20black%20yellow%20triangle.svg",
    "status_filter_label": "Active",
    "alert_level": "Advice",
    "location": "HENRY LAWSON WAY, THUDDUNGRA 2594",
    "council_area": "Hilltops",
    "type": "Grass Fire",
    "type_description": "",
    "type_icon": "/sites/default/files/incident-type-svgs/fire_1_0_5.svg",
    "fire": "Yes",
    "size": "7 ha",
    "responsible_agency": "Rural Fire Service",
    "updated": "13 Dec 2024 23:58"
  },
  {
    "title": "MOUNT PARRY CATTLE CREEK",
    "id": "https___incidents_rfs_nsw_gov_au_api_v1_incidents_578804",
    "link": "http://www.rfs.nsw.gov.au/fire-information/fires-near-me",
    "link_text": "View more",
    "latitude": "-31.7290019979999",
    "longitude": "150.333282471",
    "region": "nsw",
    "time_of_call": "13 Dec 2024 20:07:00",
    "event_type": "burnt area",
    "status": "Under control",
    "alert_level": "Not Applicable",
    "location": "MOUNT PARRY CATTLE CREEK 2339",
    "council_area": "Liverpool Plains",
    "type": "Bush Fire",
    "type_description": "",
    "type_icon": "/sites/default/files/incident-type-svgs/fire_1_0_2.svg",
    "fire": "Yes",
    "size": "15 ha",
    "responsible_agency": "Rural Fire Service",
    "updated": "13 Dec 2024 20:07"
  },
  {
    "title": "CLOWES ROAD, CURRABUBULA",
    "id": "https___incidents_rfs_nsw_gov_au_api_v1_incidents_578810",
    "link": "http://www.rfs.nsw.gov.au/fire-information/fires-near-me",
    "link_text": "View more",
    "latitude": "-31.1729414509999",
    "longitude": "150.658006668",
    "region": "nsw",
    "time_of_call": "14 Dec 2024 10:10:00",
    "event_type": "burnt area",
    "status": "Being controlled",
    "status_description": "",
    "status_icon": "/sites/default/files/alert-svgs/narrow%20black%20yellow%20triangle.svg",
    "status_filter_label": "Active",
    "alert_level": "Advice",
    "location": "328 CLOWES ROAD, CURRABUBULA 2342",
    "council_area": "Liverpool Plains",
    "type": "Bush Fire",
    "type_description": "",
    "type_icon": "/sites/default/files/incident-type-svgs/fire_1_0_2.svg",
    "fire": "Yes",
    "size": "3 ha",
    "responsible_agency": "Rural Fire Service",
    "updated": "14 Dec 2024 10:10"
  },
  {
    "title": "AIRPORT HR",
    "id": "https___incidents_rfs_nsw_gov_au_api_v1_incidents_578816",
    "link": "http://www.rfs.nsw.gov.au/fire-information/fires-near-me",
    "link_text": "View more",
    "latitude": "-34.254024505",
    "longitude": "146.065490723",
    "region": "nsw",
    "time_of_call": "14 Dec 2024 10:32:00",
    "event_type": "burnt area",
    "status": "Under control",
    "alert_level": "Planned Burn",
    "location": "GRIFFITH AIRPORT OLD AERODROME RD, GRIFFITH 2680",
    "council_area": "Griffith",
    "type": "Hazard Reduction",
    "type_description": "",
    "type_icon": "/sites/default/files/incident-type-svgs/haz-reduct-fire_1.svg",
    "fire": "Yes",
    "size": "35 ha",
    "responsible_agency": "Rural Fire Service",
    "updated": "14 Dec 2024 10:32"
  },
  {
    "title": "ROBINSONS RD, YOUNG",
    "id": "https___incidents_rfs_nsw_gov_au_api_v1_incidents_578823",
    "link": "http://www.rfs.nsw.gov.au/fire-information/fires-near-me",
    "link_text": "View more",
    "latitude": "-34.252780914",
    "longitude": "148.376983642",
    "region": "nsw",
    "time_of_call": "14 Dec 2024 00:00:00",
    "event_type": "burnt area",
    "status": "Under control",
    "alert_level": "Planned Burn",
    "location": "JENBERN PARK 145 ROBINSONS RD, YOUNG 2594",
    "council_area": "Hilltops",
    "type": "Hazard Reduction",
    "type_description": "",
    "type_icon": "/sites/default/files/incident-type-svgs/haz-reduct-fire_1.svg",
    "fire": "Yes",
    "size": "0 ha",
    "responsible_agency": "Rural Fire Service",
    "updated": "14 Dec 2024 00:00"
  },
  {
    "title": "GWYDIRFIELD RD, MOREE",
    "id": "https___incidents_rfs_nsw_gov_au_api_v1_incidents_578842",
    "link": "http://www.rfs.nsw.gov.au/fire-information/fires-near-me",
    "link_text": "View more",
    "latitude": "-29.444664001",
    "longitude": "149.880325318",
    "region": "nsw",
    "time_of_call": "14 Dec 2024 00:03:00",
    "event_type": "burnt area",
    "status": "Under control",
    "status_description": "",
    "status_icon": "/sites/default/files/alert-svgs/narrow%20black%20yellow%20triangle.svg",
    "status_filter_label": "Active",
    "alert_level": "Advice",
    "location": "494 GWYDIRFIELD RD, MOREE 2400",
    "council_area": "Moree Plains",
    "type": "Grass Fire",
    "type_description": "",
    "type_icon": "/sites/default/files/incident-type-svgs/fire_1_0_5.svg",
    "fire": "Yes",
    "size": "0 ha",
    "responsible_agency": "Rural Fire Service",
    "updated": "14 Dec 2024 00:03"
  },
  {
    "title": "LLANDILO RD, BERKSHIRE PARK",
    "id": "https___incidents_rfs_nsw_gov_au_api_v1_incidents_578872",
    "link": "http://www.rfs.nsw.gov.au/fire-information/fires-near-me",
    "link_text": "View more",
    "latitude": "-33.6708183279999",
    "longitude": "150.778930664",
    "region": "nsw",
    "time_of_call": "14 Dec 2024 07:14:00",
    "event_type": "burnt area",
    "status": "Under control",
    "alert_level": "Not Applicable",
    "location": "194 LLANDILO RD, BERKSHIRE PARK 2765",
    "council_area": "Penrith",
    "type": "Structure Fire",
    "type_description": "",
    "type_icon": "/sites/default/files/incident-type-svgs/fire-building_2.svg",
    "fire": "Yes",
    "size": "0 ha",
    "responsible_agency": "Rural Fire Service",
    "updated": "14 Dec 2024 07:14"
  },
  {
    "title": "SWAN HILL RD",
    "id": "https___incidents_rfs_nsw_gov_au_api_v1_incidents_578874",
    "link": "http://www.rfs.nsw.gov.au/fire-information/fires-near-me",
    "link_text": "View more",
    "latitude": "-35.3189468379999",
    "longitude": "143.643478394",
    "region": "nsw",
    "time_of_call": "14 Dec 2024 05:58:00",
    "event_type": "burnt area",
    "status": "Under control",
    "alert_level": "Not Applicable",
    "location": "MURRAY DOWNS ALMONDS SWAN HILL RD, MURRAY DOWNS 2734",
    "council_area": "Murray River",
    "type": "Planned Event",
    "fire": "No",
    "size": "0 ha",
    "responsible_agency": "Rural Fire Service",
    "updated": "14 Dec 2024 05:58"
  },
  {
    "title": "GWYDIR HWY, MOREE",
    "id": "https___incidents_rfs_nsw_gov_au_api_v1_incidents_578880",
    "link": "http://www.rfs.nsw.gov.au/fire-information/fires-near-me",
    "link_text": "View more",
    "latitude": "-29.478006362",
    "longitude": "149.901504516",
    "region": "nsw",
    "time_of_call": "14 Dec 2024 11:42:00",
    "event_type": "burnt area",
    "status": "Under control",
    "status_description": "",
    "status_icon": "/sites/default/files/alert-svgs/narrow%20black%20yellow%20triangle.svg",
    "status_filter_label": "Active",
    "alert_level": "Advice",
    "location": "GWYDIR HWY, MOREE 2400",
    "council_area": "Moree Plains",
    "type": "Grass Fire",
    "type_description": "",
    "type_icon": "/sites/default/files/incident-type-svgs/fire_1_0_5.svg",
    "fire": "Yes",
    "size": "0 ha",
    "responsible_agency": "Rural Fire Service",
    "updated": "14 Dec 2024 11:42"
  },
  {
    "title": "DUNVILLE LOOP RD, DUNVILLE LOOP",
    "id": "https___incidents_rfs_nsw_gov_au_api_v1_incidents_578881",
    "link": "http://www.rfs.nsw.gov.au/fire-information/fires-near-me",
    "link_text": "View more",
    "latitude": "-32.916713714",
    "longitude": "150.158432006",
    "region": "nsw",
    "time_of_call": "14 Dec 2024 10:20:00",
    "event_type": "burnt area",
    "status": "Under control",
    "alert_level": "Planned Burn",
    "location": "2039 DUNVILLE LOOP RD, DUNVILLE LOOP 2849",
    "council_area": "Lithgow",
    "type": "Hazard Reduction",
    "type_description": "",
    "type_icon": "/sites/default/files/incident-type-svgs/haz-reduct-fire_1.svg",
    "fire": "Yes",
    "size": "0 ha",
    "responsible_agency": "Rural Fire Service",
    "updated": "14 Dec 2024 10:20"
  },
  {
    "title": "CALLIGANS CREEK RD, CALLIOPE",
    "id": "https___incidents_rfs_nsw_gov_au_api_v1_incidents_578883",
    "link": "http://www.rfs.nsw.gov.au/fire-information/fires-near-me",
    "link_text": "View more",
    "latitude": "-29.6232776639999",
    "longitude": "153.078292847",
    "region": "nsw",
    "time_of_call": "14 Dec 2024 13:49:00",
    "event_type": "burnt area",
    "status": "Under control",
    "alert_level": "Planned Burn",
    "location": "4 CALLIGANS CREEK RD, CALLIOPE 2462",
    "council_area": "Clarence Valley",
    "type": "Hazard Reduction",
    "type_description": "",
    "type_icon": "/sites/default/files/incident-type-svgs/haz-reduct-fire_1.svg",
    "fire": "Yes",
    "size": "0 ha",
    "responsible_agency": "Rural Fire Service",
    "updated": "14 Dec 2024 13:49"
  },
  {
    "title": "HUME HWY",
    "id": "https___incidents_rfs_nsw_gov_au_api_v1_incidents_578887",
    "link": "http://www.rfs.nsw.gov.au/fire-information/fires-near-me",
    "link_text": "View more",
    "latitude": "-34.810668946",
    "longitude": "149.481674194",
    "region": "nsw",
    "time_of_call": "14 Dec 2024 14:26:00",
    "event_type": "burnt area",
    "status": "Under control",
    "alert_level": "Not Applicable",
    "location": "NEAR BREADALBANE PONY CLUB HUME HWY, BREADALBANE 2581",
    "council_area": "Upper Lachlan",
    "type": "Truck Fire",
    "fire": "Yes",
    "size": "0 ha",
    "responsible_agency": "Rural Fire Service",
    "updated": "14 Dec 2024 14:26"
  },
  {
    "title": "HOLBROOK WAGGA RD, HOLBROOK",
    "id": "https___incidents_rfs_nsw_gov_au_api_v1_incidents_578898",
    "link": "http://www.rfs.nsw.gov.au/fire-information/fires-near-me",
    "link_text": "View more",
    "latitude": "-35.6217193599999",
    "longitude": "147.323928833",
    "region": "nsw",
    "time_of_call": "14 Dec 2024 14:26:00",
    "event_type": "burnt area",
    "status": "Under control",
    "status_description": "",
    "status_icon": "/sites/default/files/alert-svgs/narrow%20black%20yellow%20triangle.svg",
    "status_filter_label": "Active",
    "alert_level": "Advice",
    "location": "HOLBROOK WAGGA RD, HOLBROOK 2644",
    "council_area": "Greater Hume",
    "type": "Grass Fire",
    "type_description": "",
    "type_icon": "/sites/default/files/incident-type-svgs/fire_1_0_5.svg",
    "fire": "Yes",
    "size": "5 ha",
    "responsible_agency": "Rural Fire Service",
    "updated": "14 Dec 2024 14:26"
  },
  {
    "title": "WAROO LANE, EURONGILLY",
    "id": "https___incidents_rfs_nsw_gov_au_api_v1_incidents_578904",
    "link": "http://www.rfs.nsw.gov.au/fire-information/fires-near-me",
    "link_text": "View more",
    "latitude": "-34.886989593",
    "longitude": "147.755889893",
    "region": "nsw",
    "time_of_call": "14 Dec 2024 13:35:00",
    "event_type": "burnt area",
    "status": "Under control",
    "alert_level": "Not Applicable",
    "location": "JUNAWARRA 144 WAROO LANE, EURONGILLY 2663",
    "council_area": "Junee",
    "type": "Vehicle/Equipment Fire",
    "type_description": "",
    "type_icon": "/sites/default/files/incident-type-svgs/car-fire-0_0.svg",
    "fire": "Yes",
    "size": "0 ha",
    "responsible_agency": "Rural Fire Service",
    "updated": "14 Dec 2024 13:35"
  },
  {
    "title": "PACIFIC HWY, CATHERINE HILL BAY",
    "id": "https___incidents_rfs_nsw_gov_au_api_v1_incidents_578907",
    "link": "http://www.rfs.nsw.gov.au/fire-information/fires-near-me",
    "link_text": "View more",
    "latitude": "-33.1309623719999",
    "longitude": "151.62576294",
    "region": "nsw",
    "time_of_call": "14 Dec 2024 13:39:00",
    "event_type": "burnt area",
    "status": "Responding",
    "alert_level": "Not Applicable",
    "location": "PACIFIC HWY, CATHERINE HILL BAY 2281",
    "council_area": "Lake Macquarie",
    "type": "MVA/Transport",
    "type_description": "",
    "type_icon": "/sites/default/files/incident-type-svgs/car-0_0.svg",
    "fire": "No",
    "size": "0 ha",
    "responsible_agency": "Rural Fire Service",
    "updated": "14 Dec 2024 13:39"
  },
  {
    "title": "BUSH BEND RESERVE LACHLAN ST, HAY",
    "id": "https___incidents_rfs_nsw_gov_au_api_v1_incidents_578908",
    "link": "http://www.rfs.nsw.gov.au/fire-information/fires-near-me",
    "link_text": "View more",
    "latitude": "-34.515628814",
    "longitude": "144.847351074",
    "region": "nsw",
    "time_of_call": "14 Dec 2024 13:45:00",
    "event_type": "burnt area",
    "status": "Under control",
    "alert_level": "Planned Burn",
    "location": "BUSH BEND RESERVE LACHLAN ST, HAY 2711",
    "council_area": "Hay",
    "type": "Hazard Reduction",
    "type_description": "",
    "type_icon": "/sites/default/files/incident-type-svgs/haz-reduct-fire_1.svg",
    "fire": "Yes",
    "size": "0 ha",
    "responsible_agency": "Rural Fire Service",
    "updated": "14 Dec 2024 13:45"
  },
  {
    "title": "SHEPHERD RD, SPRING CREEK",
    "id": "https___incidents_rfs_nsw_gov_au_api_v1_incidents_578909",
    "link": "http://www.rfs.nsw.gov.au/fire-information/fires-near-me",
    "link_text": "View more",
    "latitude": "-33.333641052",
    "longitude": "149.116546631",
    "region": "nsw",
    "time_of_call": "14 Dec 2024 13:57:00",
    "event_type": "burnt area",
    "status": "Responding",
    "alert_level": "Not Applicable",
    "location": "LEEWOOD 125 SHEPHERD RD, SPRING CREEK 2800",
    "council_area": "Orange",
    "type": "Assist Other Agency",
    "fire": "No",
    "size": "0 ha",
    "responsible_agency": "Rural Fire Service",
    "updated": "14 Dec 2024 13:57"
  },
  {
    "title": "SELWYN ST, EUSTON",
    "id": "https___incidents_rfs_nsw_gov_au_api_v1_incidents_578910",
    "link": "http://www.rfs.nsw.gov.au/fire-information/fires-near-me",
    "link_text": "View more",
    "latitude": "-34.5778923029999",
    "longitude": "142.742202758",
    "region": "nsw",
    "time_of_call": "14 Dec 2024 14:42:00",
    "event_type": "burnt area",
    "status": "Under control",
    "status_description": "",
    "status_icon": "/sites/default/files/alert-svgs/narrow%20black%20yellow%20triangle.svg",
    "status_filter_label": "Active",
    "alert_level": "Advice",
    "location": "SELWYN ST, EUSTON 2737",
    "council_area": "Balranald",
    "type": "Bush Fire",
    "type_description": "",
    "type_icon": "/sites/default/files/incident-type-svgs/fire_1_0_2.svg",
    "fire": "Yes",
    "size": "0 ha",
    "responsible_agency": "Rural Fire Service",
    "updated": "14 Dec 2024 14:42"
  },
  {
    "title": "WOOLSHED LANE, BIG SPRINGS",
    "id": "https___incidents_rfs_nsw_gov_au_api_v1_incidents_578912",
    "link": "http://www.rfs.nsw.gov.au/fire-information/fires-near-me",
    "link_text": "View more",
    "latitude": "-35.361721039",
    "longitude": "147.38835144",
    "region": "nsw",
    "time_of_call": "14 Dec 2024 14:22:00",
    "event_type": "burnt area",
    "status": "Responding",
    "alert_level": "Not Applicable",
    "location": "BILLOONBAH 374 WOOLSHED LANE, BIG SPRINGS 2650",
    "council_area": "Wagga Wagga",
    "type": "Grass Fire",
    "type_description": "",
    "type_icon": "/sites/default/files/incident-type-svgs/fire_1_0_5.svg",
    "fire": "Yes",
    "size": "0 ha",
    "responsible_agency": "Rural Fire Service",
    "updated": "14 Dec 2024 14:22"
  },
  {
    "title": "DONALD RD, ARMIDALE",
    "id": "https___incidents_rfs_nsw_gov_au_api_v1_incidents_578913",
    "link": "http://www.rfs.nsw.gov.au/fire-information/fires-near-me",
    "link_text": "View more",
    "latitude": "-30.4633388519999",
    "longitude": "151.721069336",
    "region": "nsw",
    "time_of_call": "14 Dec 2024 14:28:00",
    "event_type": "burnt area",
    "status": "Responding",
    "alert_level": "Not Applicable",
    "location": "179 DONALD RD, ARMIDALE 2350",
    "council_area": "Armidale",
    "type": "Grass Fire",
    "type_description": "",
    "type_icon": "/sites/default/files/incident-type-svgs/fire_1_0_5.svg",
    "fire": "Yes",
    "size": "0 ha",
    "responsible_agency": "Rural Fire Service",
    "updated": "14 Dec 2024 14:28"
  },
  {
    "title": "BELINDA ST",
    "id": "https___incidents_rfs_nsw_gov_au_api_v1_incidents_578914",
    "link": "http://www.rfs.nsw.gov.au/fire-information/fires-near-me",
    "link_text": "View more",
    "latitude": "-34.746982574",
    "longitude": "150.823181152",
    "region": "nsw",
    "time_of_call": "14 Dec 2024 14:38:00",
    "event_type": "burnt area",
    "status": "Being controlled",
    "alert_level": "Not Applicable",
    "location": "UNITING CARE MAYFLOWER VILLAGE 61 BELINDA ST, GERRINGONG 2534",
    "council_area": "Kiama",
    "type": "Fire Alarm",
    "type_description": "",
    "type_icon": "/sites/default/files/incident-type-svgs/FIRE%20ALARM_1.svg",
    "fire": "No",
    "size": "0 ha",
    "responsible_agency": "Rural Fire Service",
    "updated": "14 Dec 2024 14:38"
  },
  {
    "title": "OPHIR RD, ROCK FOREST",
    "id": "https___incidents_rfs_nsw_gov_au_api_v1_incidents_578915",
    "link": "http://www.rfs.nsw.gov.au/fire-information/fires-near-me",
    "link_text": "View more",
    "latitude": "-33.3418731689999",
    "longitude": "149.377258301",
    "region": "nsw",
    "time_of_call": "14 Dec 2024 14:38:00",
    "event_type": "burnt area",
    "status": "Responding",
    "alert_level": "Not Applicable",
    "location": "ROCK FOREST 1846 OPHIR RD, ROCK FOREST 2795",
    "council_area": "Bathurst",
    "type": "Fire Alarm",
    "type_description": "",
    "type_icon": "/sites/default/files/incident-type-svgs/FIRE%20ALARM_1.svg",
    "fire": "No",
    "size": "0 ha",
    "responsible_agency": "Rural Fire Service",
    "updated": "14 Dec 2024 14:38"
  }
]
