[
  {
    "title": "ANIMAL RESCUE - LYNEHAM",
    "id": "002459-07022024",
    "latitude": "-35.2320225",
    "longitude": "149.145307",
    "node": "",
    "description": "",
    "link": "",
    "link_text": "",
    "updated_tag": false,
    "region": "act",
    "image_urls": [],
    "weight": 0,
    "incident": "ANIMAL RESCUE - LYNEHAM",
    "location": "ADMINISTRATION BLD, FLEMINGTON ROAD, LYNEHAM, 2602",
    "status": "Out / Completed",
    "status_description": "Out / Completed description\r\n",
    "status_icon": "https://esa.act.gov.au/sites/default/files/status-svgs/narrow%20black%20triangle_1_2.svg",
    "status_filter_label": "Out / Completed",
    "suburb": "LYNEHAM",
    "type": "ANIMAL RESCUE",
    "type_description": "",
    "type_icon": "https://esa.act.gov.au/sites/default/files/incident-type-svgs/animal-rescue_0.svg",
    "agency": "Fire",
    "incident_number": "002459-07022024",
    "updated": "07 Feb 2024 21:18:11.543",
    "time_of_call": "07 Feb 2024 20:29:26"
  },
  {
    "title": "AMBULANCE RESPONSE - GREENWAY",
    "id": "007437-07022024",
    "latitude": "-35.411775",
    "longitude": "149.064968",
    "node": "",
    "description": "",
    "link": "",
    "link_text": "",
    "updated_tag": false,
    "region": "act",
    "image_urls": [],
    "weight": 0,
    "incident": "AMBULANCE RESPONSE - GREENWAY",
    "location": "GREENWAY",
    "status": "On Scene",
    "status_description": "",
    "status_icon": "https://esa.act.gov.au/sites/default/files/type-ambulance-svgs/narrow%20ambulance%20blue-0_1.svg",
    "status_filter_label": "On Scene",
    "suburb": "GREENWAY",
    "type": "AMBULANCE RESPONSE",
    "agency": "Ambulance",
    "incident_number": "007437-07022024",
    "updated": "07 Feb 2024 20:23:06.73",
    "time_of_call": "07 Feb 2024 16:40:12"
  },
  {
    "title": "AMBULANCE RESPONSE - DUNLOP",
    "id": "007454-07022024",
    "latitude": "-35.193951",
    "longitude": "149.019471",
    "node": "",
    "description": "",
    "link": "",
    "link_text": "",
    "updated_tag": false,
    "region": "act",
    "image_urls": [],
    "weight": 0,
    "incident": "AMBULANCE RESPONSE - DUNLOP",
    "location": "DUNLOP",
    "status": "Resource Allocation Pending",
    "status_description": "",
    "status_icon": "https://esa.act.gov.au/sites/default/files/type-ambulance-svgs/narrow%20ambulance%20blue-0_2.svg",
    "status_filter_label": "Resource Allocation Pending",
    "suburb": "DUNLOP",
    "type": "AMBULANCE RESPONSE",
    "agency": "Ambulance",
    "incident_number": "007454-07022024",
    "updated": "07 Feb 2024 20:04:27.18",
    "time_of_call": "07 Feb 2024 17:46:15"
  },
  {
    "title": "AMBULANCE RESPONSE - RICHARDSON",
    "id": "007457-07022024",
    "latitude": "-35.428715",
    "longitude": "149.111133",
    "node": "",
    "description": "",
    "link": "",
    "link_text": "",
    "updated_tag": false,
    "region": "act",
    "image_urls": [],
    "weight": 0,
    "incident": "AMBULANCE RESPONSE - RICHARDSON",
    "location": "RICHARDSON",
    "status": "Resource Allocation Pending",
    "status_description": "",
    "status_icon": "https://esa.act.gov.au/sites/default/files/type-ambulance-svgs/narrow%20ambulance%20blue-0_2.svg",
    "status_filter_label": "Resource Allocation Pending",
    "suburb": "RICHARDSON",
    "type": "AMBULANCE RESPONSE",
    "agency": "Ambulance",
    "incident_number": "007457-07022024",
    "updated": "07 Feb 2024 17:55:39.977",
    "time_of_call": "07 Feb 2024 17:51:11"
  },
  {
    "title": "AMBULANCE RESPONSE - RICHARDSON",
    "id": "007458-07022024",
    "latitude": "-35.428715",
    "longitude": "149.111133",
    "node": "",
    "description": "",
    "link": "",
    "link_text": "",
    "updated_tag": false,
    "region": "act",
    "image_urls": [],
    "weight": 0,
    "incident": "AMBULANCE RESPONSE - RICHARDSON",
    "location": "RICHARDSON",
    "status": "Resource Allocation Pending",
    "status_description": "",
    "status_icon": "https://esa.act.gov.au/sites/default/files/type-ambulance-svgs/narrow%20ambulance%20blue-0_2.svg",
    "status_filter_label": "Resource Allocation Pending",
    "suburb": "RICHARDSON",
    "type": "AMBULANCE RESPONSE",
    "agency": "Ambulance",
    "incident_number": "007458-07022024",
    "updated": "07 Feb 2024 18:03:03.563",
    "time_of_call": "07 Feb 2024 17:53:39"
  },
  {
    "title": "AMBULANCE RESPONSE - CURTIN",
    "id": "007472-07022024",
    "latitude": "-35.326585",
    "longitude": "149.076856",
    "node": "",
    "description": "",
    "link": "",
    "link_text": "",
    "updated_tag": false,
    "region": "act",
    "image_urls": [],
    "weight": 0,
    "incident": "AMBULANCE RESPONSE - CURTIN",
    "location": "CURTIN",
    "status": "Units On Route",
    "status_description": "",
    "status_icon": "https://esa.act.gov.au/sites/default/files/type-ambulance-svgs/narrow%20ambulance%20blue-0_3.svg",
    "status_filter_label": "Units On Route",
    "suburb": "CURTIN",
    "type": "AMBULANCE RESPONSE",
    "agency": "Ambulance",
    "incident_number": "007472-07022024",
    "updated": "07 Feb 2024 21:34:00.433",
    "time_of_call": "07 Feb 2024 18:33:18"
  },
  {
    "title": "AMBULANCE RESPONSE - PHILLIP",
    "id": "007475-07022024",
    "latitude": "-35.348136",
    "longitude": "149.090018",
    "node": "",
    "description": "",
    "link": "",
    "link_text": "",
    "updated_tag": false,
    "region": "act",
    "image_urls": [],
    "weight": 0,
    "incident": "AMBULANCE RESPONSE - PHILLIP",
    "location": "PHILLIP",
    "status": "Resource Allocation Pending",
    "status_description": "",
    "status_icon": "https://esa.act.gov.au/sites/default/files/type-ambulance-svgs/narrow%20ambulance%20blue-0_2.svg",
    "status_filter_label": "Resource Allocation Pending",
    "suburb": "PHILLIP",
    "type": "AMBULANCE RESPONSE",
    "agency": "Ambulance",
    "incident_number": "007475-07022024",
    "updated": "07 Feb 2024 18:44:26.35",
    "time_of_call": "07 Feb 2024 18:38:46"
  },
  {
    "title": "AMBULANCE RESPONSE - KAMBAH",
    "id": "007476-07022024",
    "latitude": "-35.384074",
    "longitude": "149.06111",
    "node": "",
    "description": "",
    "link": "",
    "link_text": "",
    "updated_tag": false,
    "region": "act",
    "image_urls": [],
    "weight": 0,
    "incident": "AMBULANCE RESPONSE - KAMBAH",
    "location": "KAMBAH",
    "status": "Resource Allocation Pending",
    "status_description": "",
    "status_icon": "https://esa.act.gov.au/sites/default/files/type-ambulance-svgs/narrow%20ambulance%20blue-0_2.svg",
    "status_filter_label": "Resource Allocation Pending",
    "suburb": "KAMBAH",
    "type": "AMBULANCE RESPONSE",
    "agency": "Ambulance",
    "incident_number": "007476-07022024",
    "updated": "07 Feb 2024 20:59:18.573",
    "time_of_call": "07 Feb 2024 19:01:09"
  },
  {
    "title": "AMBULANCE RESPONSE - GREENWAY",
    "id": "007478-07022024",
    "latitude": "-35.411775",
    "longitude": "149.064968",
    "node": "",
    "description": "",
    "link": "",
    "link_text": "",
    "updated_tag": false,
    "region": "act",
    "image_urls": [],
    "weight": 0,
    "incident": "AMBULANCE RESPONSE - GREENWAY",
    "location": "GREENWAY",
    "status": "On Scene",
    "status_description": "",
    "status_icon": "https://esa.act.gov.au/sites/default/files/type-ambulance-svgs/narrow%20ambulance%20blue-0_1.svg",
    "status_filter_label": "On Scene",
    "suburb": "GREENWAY",
    "type": "AMBULANCE RESPONSE",
    "agency": "Ambulance",
    "incident_number": "007478-07022024",
    "updated": "07 Feb 2024 21:22:09.923",
    "time_of_call": "07 Feb 2024 19:09:03"
  },
  {
    "title": "AMBULANCE RESPONSE - KALEEN",
    "id": "007481-07022024",
    "latitude": "-35.227626",
    "longitude": "149.105773",
    "node": "",
    "description": "",
    "link": "",
    "link_text": "",
    "updated_tag": false,
    "region": "act",
    "image_urls": [],
    "weight": 0,
    "incident": "AMBULANCE RESPONSE - KALEEN",
    "location": "KALEEN",
    "status": "Resource Allocation Pending",
    "status_description": "",
    "status_icon": "https://esa.act.gov.au/sites/default/files/type-ambulance-svgs/narrow%20ambulance%20blue-0_2.svg",
    "status_filter_label": "Resource Allocation Pending",
    "suburb": "KALEEN",
    "type": "AMBULANCE RESPONSE",
    "agency": "Ambulance",
    "incident_number": "007481-07022024",
    "updated": "07 Feb 2024 19:50:30.123",
    "time_of_call": "07 Feb 2024 19:34:59"
  },
  {
    "title": "AMBULANCE RESPONSE - PHILLIP",
    "id": "007485-07022024",
    "latitude": "-35.348136",
    "longitude": "149.090018",
    "node": "",
    "description": "",
    "link": "",
    "link_text": "",
    "updated_tag": false,
    "region": "act",
    "image_urls": [],
    "weight": 0,
    "incident": "AMBULANCE RESPONSE - PHILLIP",
    "location": "PHILLIP",
    "status": "Resource Allocation Pending",
    "status_description": "",
    "status_icon": "https://esa.act.gov.au/sites/default/files/type-ambulance-svgs/narrow%20ambulance%20blue-0_2.svg",
    "status_filter_label": "Resource Allocation Pending",
    "suburb": "PHILLIP",
    "type": "AMBULANCE RESPONSE",
    "agency": "Ambulance",
    "incident_number": "007485-07022024",
    "updated": "07 Feb 2024 20:17:57.41",
    "time_of_call": "07 Feb 2024 19:52:50"
  },
  {
    "title": "AMBULANCE RESPONSE - BRADDON",
    "id": "007488-07022024",
    "latitude": "-35.270314",
    "longitude": "149.135874",
    "node": "",
    "description": "",
    "link": "",
    "link_text": "",
    "updated_tag": false,
    "region": "act",
    "image_urls": [],
    "weight": 0,
    "incident": "AMBULANCE RESPONSE - BRADDON",
    "location": "BRADDON",
    "status": "On Scene",
    "status_description": "",
    "status_icon": "https://esa.act.gov.au/sites/default/files/type-ambulance-svgs/narrow%20ambulance%20blue-0_1.svg",
    "status_filter_label": "On Scene",
    "suburb": "BRADDON",
    "type": "AMBULANCE RESPONSE",
    "agency": "Ambulance",
    "incident_number": "007488-07022024",
    "updated": "07 Feb 2024 21:18:31.233",
    "time_of_call": "07 Feb 2024 20:07:36"
  },
  {
    "title": "AMBULANCE RESPONSE - FRASER",
    "id": "007489-07022024",
    "latitude": "-35.189989",
    "longitude": "149.043755",
    "node": "",
    "description": "",
    "link": "",
    "link_text": "",
    "updated_tag": false,
    "region": "act",
    "image_urls": [],
    "weight": 0,
    "incident": "AMBULANCE RESPONSE - FRASER",
    "location": "FRASER",
    "status": "Resource Allocation Pending",
    "status_description": "",
    "status_icon": "https://esa.act.gov.au/sites/default/files/type-ambulance-svgs/narrow%20ambulance%20blue-0_2.svg",
    "status_filter_label": "Resource Allocation Pending",
    "suburb": "FRASER",
    "type": "AMBULANCE RESPONSE",
    "agency": "Ambulance",
    "incident_number": "007489-07022024",
    "updated": "07 Feb 2024 20:15:51.15",
    "time_of_call": "07 Feb 2024 20:09:14"
  },
  {
    "title": "AMBULANCE RESPONSE - HOLT",
    "id": "007490-07022024",
    "latitude": "-35.224201",
    "longitude": "149.013141",
    "node": "",
    "description": "",
    "link": "",
    "link_text": "",
    "updated_tag": false,
    "region": "act",
    "image_urls": [],
    "weight": 0,
    "incident": "AMBULANCE RESPONSE - HOLT",
    "location": "HOLT",
    "status": "Resource Allocation Pending",
    "status_description": "",
    "status_icon": "https://esa.act.gov.au/sites/default/files/type-ambulance-svgs/narrow%20ambulance%20blue-0_2.svg",
    "status_filter_label": "Resource Allocation Pending",
    "suburb": "HOLT",
    "type": "AMBULANCE RESPONSE",
    "agency": "Ambulance",
    "incident_number": "007490-07022024",
    "updated": "07 Feb 2024 21:41:50.44",
    "time_of_call": "07 Feb 2024 20:10:00"
  },
  {
    "title": "AMBULANCE RESPONSE - BONNER",
    "id": "007492-07022024",
    "latitude": "-35.155183",
    "longitude": "149.143165",
    "node": "",
    "description": "",
    "link": "",
    "link_text": "",
    "updated_tag": false,
    "region": "act",
    "image_urls": [],
    "weight": 0,
    "incident": "AMBULANCE RESPONSE - BONNER",
    "location": "BONNER",
    "status": "Resource Allocation Pending",
    "status_description": "",
    "status_icon": "https://esa.act.gov.au/sites/default/files/type-ambulance-svgs/narrow%20ambulance%20blue-0_2.svg",
    "status_filter_label": "Resource Allocation Pending",
    "suburb": "BONNER",
    "type": "AMBULANCE RESPONSE",
    "agency": "Ambulance",
    "incident_number": "007492-07022024",
    "updated": "07 Feb 2024 21:12:27.447",
    "time_of_call": "07 Feb 2024 20:14:05"
  },
  {
    "title": "AMBULANCE RESPONSE - KAMBAH",
    "id": "007493-07022024",
    "latitude": "-35.384074",
    "longitude": "149.06111",
    "node": "",
    "description": "",
    "link": "",
    "link_text": "",
    "updated_tag": false,
    "region": "act",
    "image_urls": [],
    "weight": 0,
    "incident": "AMBULANCE RESPONSE - KAMBAH",
    "location": "KAMBAH",
    "status": "Resource Allocation Pending",
    "status_description": "",
    "status_icon": "https://esa.act.gov.au/sites/default/files/type-ambulance-svgs/narrow%20ambulance%20blue-0_2.svg",
    "status_filter_label": "Resource Allocation Pending",
    "suburb": "KAMBAH",
    "type": "AMBULANCE RESPONSE",
    "agency": "Ambulance",
    "incident_number": "007493-07022024",
    "updated": "07 Feb 2024 20:33:47.22",
    "time_of_call": "07 Feb 2024 20:19:36"
  },
  {
    "title": "AMBULANCE RESPONSE - CHARNWOOD",
    "id": "007496-07022024",
    "latitude": "-35.200338",
    "longitude": "149.036735",
    "node": "",
    "description": "",
    "link": "",
    "link_text": "",
    "updated_tag": false,
    "region": "act",
    "image_urls": [],
    "weight": 0,
    "incident": "AMBULANCE RESPONSE - CHARNWOOD",
    "location": "CHARNWOOD",
    "status": "Resource Allocation Pending",
    "status_description": "",
    "status_icon": "https://esa.act.gov.au/sites/default/files/type-ambulance-svgs/narrow%20ambulance%20blue-0_2.svg",
    "status_filter_label": "Resource Allocation Pending",
    "suburb": "CHARNWOOD",
    "type": "AMBULANCE RESPONSE",
    "agency": "Ambulance",
    "incident_number": "007496-07022024",
    "updated": "07 Feb 2024 20:49:34.737",
    "time_of_call": "07 Feb 2024 20:25:33"
  },
  {
    "title": "AMBULANCE RESPONSE - WARAMANGA",
    "id": "007498-07022024",
    "latitude": "-35.353501",
    "longitude": "149.06067",
    "node": "",
    "description": "",
    "link": "",
    "link_text": "",
    "updated_tag": false,
    "region": "act",
    "image_urls": [],
    "weight": 0,
    "incident": "AMBULANCE RESPONSE - WARAMANGA",
    "location": "WARAMANGA",
    "status": "On Scene",
    "status_description": "",
    "status_icon": "https://esa.act.gov.au/sites/default/files/type-ambulance-svgs/narrow%20ambulance%20blue-0_1.svg",
    "status_filter_label": "On Scene",
    "suburb": "WARAMANGA",
    "type": "AMBULANCE RESPONSE",
    "agency": "Ambulance",
    "incident_number": "007498-07022024",
    "updated": "07 Feb 2024 21:11:37.743",
    "time_of_call": "07 Feb 2024 20:34:18"
  },
  {
    "title": "AMBULANCE RESPONSE - TAYLOR",
    "id": "007499-07022024",
    "latitude": "-35.147416",
    "longitude": "149.105924",
    "node": "",
    "description": "",
    "link": "",
    "link_text": "",
    "updated_tag": false,
    "region": "act",
    "image_urls": [],
    "weight": 0,
    "incident": "AMBULANCE RESPONSE - TAYLOR",
    "location": "TAYLOR",
    "status": "On Scene",
    "status_description": "",
    "status_icon": "https://esa.act.gov.au/sites/default/files/type-ambulance-svgs/narrow%20ambulance%20blue-0_1.svg",
    "status_filter_label": "On Scene",
    "suburb": "TAYLOR",
    "type": "AMBULANCE RESPONSE",
    "agency": "Ambulance",
    "incident_number": "007499-07022024",
    "updated": "07 Feb 2024 21:42:11.177",
    "time_of_call": "07 Feb 2024 20:36:16"
  },
  {
    "title": "AMBULANCE RESPONSE - WANNIASSA",
    "id": "007500-07022024",
    "latitude": "-35.399113",
    "longitude": "149.091978",
    "node": "",
    "description": "",
    "link": "",
    "link_text": "",
    "updated_tag": false,
    "region": "act",
    "image_urls": [],
    "weight": 0,
    "incident": "AMBULANCE RESPONSE - WANNIASSA",
    "location": "WANNIASSA",
    "status": "On Scene",
    "status_description": "",
    "status_icon": "https://esa.act.gov.au/sites/default/files/type-ambulance-svgs/narrow%20ambulance%20blue-0_1.svg",
    "status_filter_label": "On Scene",
    "suburb": "WANNIASSA",
    "type": "AMBULANCE RESPONSE",
    "agency": "Ambulance",
    "incident_number": "007500-07022024",
    "updated": "07 Feb 2024 21:35:21.43",
    "time_of_call": "07 Feb 2024 20:38:23"
  },
  {
    "title": "AMBULANCE RESPONSE - FLYNN",
    "id": "007501-07022024",
    "latitude": "-35.207317",
    "longitude": "149.042983",
    "node": "",
    "description": "",
    "link": "",
    "link_text": "",
    "updated_tag": false,
    "region": "act",
    "image_urls": [],
    "weight": 0,
    "incident": "AMBULANCE RESPONSE - FLYNN",
    "location": "FLYNN",
    "status": "Resource Allocation Pending",
    "status_description": "",
    "status_icon": "https://esa.act.gov.au/sites/default/files/type-ambulance-svgs/narrow%20ambulance%20blue-0_2.svg",
    "status_filter_label": "Resource Allocation Pending",
    "suburb": "FLYNN",
    "type": "AMBULANCE RESPONSE",
    "agency": "Ambulance",
    "incident_number": "007501-07022024",
    "updated": "07 Feb 2024 20:48:05.62",
    "time_of_call": "07 Feb 2024 20:40:15"
  },
  {
    "title": "AMBULANCE RESPONSE - CITY",
    "id": "007503-07022024",
    "latitude": "-35.282068",
    "longitude": "149.12873",
    "node": "",
    "description": "",
    "link": "",
    "link_text": "",
    "updated_tag": false,
    "region": "act",
    "image_urls": [],
    "weight": 0,
    "incident": "AMBULANCE RESPONSE - CITY",
    "location": "CITY",
    "status": "Resource Allocation Pending",
    "status_description": "",
    "status_icon": "https://esa.act.gov.au/sites/default/files/type-ambulance-svgs/narrow%20ambulance%20blue-0_2.svg",
    "status_filter_label": "Resource Allocation Pending",
    "suburb": "CITY",
    "type": "AMBULANCE RESPONSE",
    "agency": "Ambulance",
    "incident_number": "007503-07022024",
    "updated": "07 Feb 2024 20:57:16.897",
    "time_of_call": "07 Feb 2024 20:52:16"
  },
  {
    "title": "AMBULANCE RESPONSE - CITY",
    "id": "007504-07022024",
    "latitude": "-35.282068",
    "longitude": "149.12873",
    "node": "",
    "description": "",
    "link": "",
    "link_text": "",
    "updated_tag": false,
    "region": "act",
    "image_urls": [],
    "weight": 0,
    "incident": "AMBULANCE RESPONSE - CITY",
    "location": "CITY",
    "status": "On Scene",
    "status_description": "",
    "status_icon": "https://esa.act.gov.au/sites/default/files/type-ambulance-svgs/narrow%20ambulance%20blue-0_1.svg",
    "status_filter_label": "On Scene",
    "suburb": "CITY",
    "type": "AMBULANCE RESPONSE",
    "agency": "Ambulance",
    "incident_number": "007504-07022024",
    "updated": "07 Feb 2024 21:44:11.883",
    "time_of_call": "07 Feb 2024 21:04:10"
  },
  {
    "title": "AMBULANCE RESPONSE - CHARNWOOD",
    "id": "007506-07022024",
    "latitude": "-35.200338",
    "longitude": "149.036735",
    "node": "",
    "description": "",
    "link": "",
    "link_text": "",
    "updated_tag": false,
    "region": "act",
    "image_urls": [],
    "weight": 0,
    "incident": "AMBULANCE RESPONSE - CHARNWOOD",
    "location": "CHARNWOOD",
    "status": "Units On Route",
    "status_description": "",
    "status_icon": "https://esa.act.gov.au/sites/default/files/type-ambulance-svgs/narrow%20ambulance%20blue-0_3.svg",
    "status_filter_label": "Units On Route",
    "suburb": "CHARNWOOD",
    "type": "AMBULANCE RESPONSE",
    "agency": "Ambulance",
    "incident_number": "007506-07022024",
    "updated": "07 Feb 2024 21:42:28.22",
    "time_of_call": "07 Feb 2024 21:15:32"
  },
  {
    "title": "AMBULANCE RESPONSE - CHIFLEY",
    "id": "007509-07022024",
    "latitude": "-35.351526",
    "longitude": "149.076955",
    "node": "",
    "description": "",
    "link": "",
    "link_text": "",
    "updated_tag": false,
    "region": "act",
    "image_urls": [],
    "weight": 0,
    "incident": "AMBULANCE RESPONSE - CHIFLEY",
    "location": "CHIFLEY",
    "status": "Resource Allocation Pending",
    "status_description": "",
    "status_icon": "https://esa.act.gov.au/sites/default/files/type-ambulance-svgs/narrow%20ambulance%20blue-0_2.svg",
    "status_filter_label": "Resource Allocation Pending",
    "suburb": "CHIFLEY",
    "type": "AMBULANCE RESPONSE",
    "agency": "Ambulance",
    "incident_number": "007509-07022024",
    "updated": "07 Feb 2024 21:47:40.077",
    "time_of_call": "07 Feb 2024 21:36:12"
  },
  {
    "title": "SANDON RIVER",
    "id": "https___incidents_rfs_nsw_gov_au_api_v1_incidents_533320",
    "latitude": "-29.777889252",
    "longitude": "153.279541016",
    "link": "http://www.rfs.nsw.gov.au/fire-information/fires-near-me",
    "link_text": "View more",
    "region": "nsw",
    "time_of_call": "07 Feb 2024 09:49:32",
    "status": "Under control",
    "status_description": "",
    "status_icon": "https://esa.act.gov.au/sites/default/files/alert-svgs/narrow%20black%20yellow%20triangle.svg",
    "status_filter_label": "Active",
    "alert_level": "Advice",
    "location": "MINNIE WATER 2462",
    "council_area": "Clarence Valley",
    "type": "Bush Fire",
    "type_description": "",
    "type_icon": "https://esa.act.gov.au/sites/default/files/incident-type-svgs/fire_1_0_2.svg",
    "fire": "Yes",
    "size": "4246 ha",
    "responsible_agency": "NSW National Parks and Wildlife Service",
    "updated": "7 Feb 2024 16:46"
  },
  {
    "title": "SHALLOW BAY RD, COOMBA BAY",
    "id": "https___incidents_rfs_nsw_gov_au_api_v1_incidents_533728",
    "latitude": "-32.230564118",
    "longitude": "152.401535034",
    "link": "http://www.rfs.nsw.gov.au/fire-information/fires-near-me",
    "link_text": "View more",
    "region": "nsw",
    "time_of_call": "07 Feb 2024 09:49:32",
    "status": "Under control",
    "status_description": "",
    "status_icon": "https://esa.act.gov.au/sites/default/files/alert-svgs/narrow%20black%20yellow%20triangle.svg",
    "status_filter_label": "Active",
    "alert_level": "Advice",
    "location": "SHALLOW BAY RD, COOMBA BAY 2428",
    "council_area": "Mid-Coast",
    "type": "Bush Fire",
    "type_description": "",
    "type_icon": "https://esa.act.gov.au/sites/default/files/incident-type-svgs/fire_1_0_2.svg",
    "fire": "Yes",
    "size": "330 ha",
    "responsible_agency": "Rural Fire Service",
    "updated": "7 Feb 2024 14:20"
  },
  {
    "title": "FCNSW WRB Wild Cattle Creek 012",
    "id": "https___incidents_rfs_nsw_gov_au_api_v1_incidents_534065",
    "latitude": "-30.168281921",
    "longitude": "152.823772431",
    "link": "http://www.rfs.nsw.gov.au/fire-information/fires-near-me",
    "link_text": "View more",
    "region": "nsw",
    "time_of_call": "07 Feb 2024 09:49:32",
    "status": "Under control",
    "alert_level": "Planned Burn",
    "location": "Timmsvale Rd, 7.5km NW of Ulong",
    "council_area": "Coffs Harbour",
    "type": "Hazard Reduction",
    "type_description": "",
    "type_icon": "https://esa.act.gov.au/sites/default/files/incident-type-svgs/haz-reduct-fire_1.svg",
    "fire": "Yes",
    "size": "105 ha",
    "responsible_agency": "Forestry Corporation of NSW",
    "updated": "7 Feb 2024 14:35"
  },
  {
    "title": "PACIFIC HWY, KARUAH",
    "id": "https___incidents_rfs_nsw_gov_au_api_v1_incidents_534321",
    "latitude": "-32.6315241579999",
    "longitude": "151.893062212",
    "link": "http://www.rfs.nsw.gov.au/fire-information/fires-near-me",
    "link_text": "View more",
    "region": "nsw",
    "time_of_call": "07 Feb 2024 09:49:32",
    "status": "Under control",
    "status_description": "",
    "status_icon": "https://esa.act.gov.au/sites/default/files/alert-svgs/narrow%20black%20yellow%20triangle.svg",
    "status_filter_label": "Active",
    "alert_level": "Advice",
    "location": "PACIFIC HWY, KARUAH 2324",
    "council_area": "Port Stephens",
    "type": "Bush Fire",
    "type_description": "",
    "type_icon": "https://esa.act.gov.au/sites/default/files/incident-type-svgs/fire_1_0_2.svg",
    "fire": "Yes",
    "size": "1103 ha",
    "responsible_agency": "Forestry Corporation of NSW",
    "updated": "7 Feb 2024 15:03"
  },
  {
    "title": "MURRELLS RD, OLNEY",
    "id": "https___incidents_rfs_nsw_gov_au_api_v1_incidents_534372",
    "latitude": "-32.952619117",
    "longitude": "151.459502221",
    "link": "http://www.rfs.nsw.gov.au/fire-information/fires-near-me",
    "link_text": "View more",
    "region": "nsw",
    "time_of_call": "07 Feb 2024 09:49:32",
    "status": "Under control",
    "status_description": "",
    "status_icon": "https://esa.act.gov.au/sites/default/files/alert-svgs/narrow%20black%20yellow%20triangle.svg",
    "status_filter_label": "Active",
    "alert_level": "Advice",
    "location": "MURRELLS RD, OLNEY 2325",
    "council_area": "Cessnock",
    "type": "Bush Fire",
    "type_description": "",
    "type_icon": "https://esa.act.gov.au/sites/default/files/incident-type-svgs/fire_1_0_2.svg",
    "fire": "Yes",
    "size": "8 ha",
    "responsible_agency": "Forestry Corporation of NSW",
    "updated": "7 Feb 2024 09:31"
  },
  {
    "title": "GIINAGAY WAY, VALLA",
    "id": "https___incidents_rfs_nsw_gov_au_api_v1_incidents_534577",
    "latitude": "-30.5636272429999",
    "longitude": "153.009811401",
    "link": "http://www.rfs.nsw.gov.au/fire-information/fires-near-me",
    "link_text": "View more",
    "region": "nsw",
    "time_of_call": "07 Feb 2024 09:49:32",
    "status": "Under control",
    "alert_level": "Not Applicable",
    "location": "3340 GIINAGAY WAY, VALLA 2448",
    "council_area": "Bellingen",
    "type": "Burn off",
    "type_description": "",
    "type_icon": "https://esa.act.gov.au/sites/default/files/incident-type-svgs/fire_1_0_1.svg",
    "fire": "Yes",
    "size": "0 ha",
    "responsible_agency": "Rural Fire Service",
    "updated": "7 Feb 2024 17:09"
  },
  {
    "title": "MILVALE LANE, STOCKINBINGAL",
    "id": "https___incidents_rfs_nsw_gov_au_api_v1_incidents_534603",
    "latitude": "-34.3958778379999",
    "longitude": "147.880325318",
    "link": "http://www.rfs.nsw.gov.au/fire-information/fires-near-me",
    "link_text": "View more",
    "region": "nsw",
    "time_of_call": "07 Feb 2024 09:49:32",
    "status": "Under control",
    "alert_level": "Not Applicable",
    "location": "SEYMOUR 811 MILVALE LANE, STOCKINBINGAL 2725",
    "council_area": "Cootamundra-Gundagai",
    "type": "Haystack fire",
    "type_description": "",
    "type_icon": "https://esa.act.gov.au/sites/default/files/incident-type-svgs/fire_1_0_6.svg",
    "fire": "Yes",
    "size": "0 ha",
    "responsible_agency": "Rural Fire Service",
    "updated": "7 Feb 2024 18:10"
  },
  {
    "title": "LACKERSTEENS RD, SOMERSBY",
    "id": "https___incidents_rfs_nsw_gov_au_api_v1_incidents_534627",
    "latitude": "-33.3728904719999",
    "longitude": "151.299789428",
    "link": "http://www.rfs.nsw.gov.au/fire-information/fires-near-me",
    "link_text": "View more",
    "region": "nsw",
    "time_of_call": "07 Feb 2024 09:49:32",
    "status": "Under control",
    "alert_level": "Not Applicable",
    "location": "90 LACKERSTEENS RD, SOMERSBY 2250",
    "council_area": "Central Coast",
    "type": "Other",
    "fire": "Yes",
    "size": "0 ha",
    "responsible_agency": "Rural Fire Service",
    "updated": "7 Feb 2024 14:28"
  },
  {
    "title": "FCNSW WRB Orara East 022",
    "id": "https___incidents_rfs_nsw_gov_au_api_v1_incidents_534719",
    "latitude": "-30.179152382",
    "longitude": "153.130145073",
    "link": "http://www.rfs.nsw.gov.au/fire-information/fires-near-me",
    "link_text": "View more",
    "region": "nsw",
    "time_of_call": "07 Feb 2024 09:49:32",
    "status": "Under control",
    "alert_level": "Planned Burn",
    "location": "Bell Road Orara East SF, 3.5km NW of Moonee Beach",
    "council_area": "Coffs Harbour",
    "type": "Hazard Reduction",
    "type_description": "",
    "type_icon": "https://esa.act.gov.au/sites/default/files/incident-type-svgs/haz-reduct-fire_1.svg",
    "fire": "Yes",
    "size": "40 ha",
    "responsible_agency": "Forestry Corporation of NSW",
    "updated": "7 Feb 2024 15:18"
  },
  {
    "title": "DUCK CREEK RD, DUCK CREEK",
    "id": "https___incidents_rfs_nsw_gov_au_api_v1_incidents_534721",
    "latitude": "-28.662578583",
    "longitude": "152.606689453",
    "link": "http://www.rfs.nsw.gov.au/fire-information/fires-near-me",
    "link_text": "View more",
    "region": "nsw",
    "time_of_call": "07 Feb 2024 09:49:32",
    "status": "Under control",
    "alert_level": "Not Applicable",
    "location": "119 DUCK CREEK RD, DUCK CREEK 2469",
    "council_area": "Kyogle",
    "type": "Assist Other Agency",
    "fire": "No",
    "size": "0 ha",
    "responsible_agency": "Rural Fire Service",
    "updated": "7 Feb 2024 16:29"
  },
  {
    "title": "HOLLANDS LAKE RD, COOMEALLA",
    "id": "https___incidents_rfs_nsw_gov_au_api_v1_incidents_534732",
    "latitude": "-34.103160858",
    "longitude": "142.114517212",
    "link": "http://www.rfs.nsw.gov.au/fire-information/fires-near-me",
    "link_text": "View more",
    "region": "nsw",
    "time_of_call": "07 Feb 2024 09:49:32",
    "status": "Under control",
    "alert_level": "Not Applicable",
    "location": "HOLLANDS LAKE RD, COOMEALLA 2717",
    "council_area": "Wentworth",
    "type": "Other",
    "fire": "Yes",
    "size": "0 ha",
    "responsible_agency": "Rural Fire Service",
    "updated": "7 Feb 2024 21:22"
  },
  {
    "title": "Clarence St, Ilarwill",
    "id": "https___incidents_rfs_nsw_gov_au_api_v1_incidents_534734",
    "latitude": "-29.478801727",
    "longitude": "153.181915284",
    "link": "http://www.rfs.nsw.gov.au/fire-information/fires-near-me",
    "link_text": "View more",
    "region": "nsw",
    "time_of_call": "07 Feb 2024 09:49:32",
    "status": "Under control",
    "status_description": "",
    "status_icon": "https://esa.act.gov.au/sites/default/files/alert-svgs/narrow%20black%20yellow%20triangle.svg",
    "status_filter_label": "Active",
    "alert_level": "Advice",
    "location": "Clarence St, Ilarwill, NSW 2463",
    "council_area": "Clarence Valley",
    "type": "Grass Fire",
    "type_description": "",
    "type_icon": "https://esa.act.gov.au/sites/default/files/incident-type-svgs/fire_1_0_5.svg",
    "fire": "Yes",
    "size": "0 ha",
    "responsible_agency": "Fire and Rescue NSW",
    "updated": "7 Feb 2024 21:15"
  }
]
